sim/sim/aho_corasick.v
// ============================================================
// HASS - Aho-Corasick Signature Matching Engine
// Target: Digilent Arty A7-100T (Artix-7 XC7A100T)
// ============================================================

module aho_corasick #(
    parameter NUM_STATES    = 1024,   // max trie states
    parameter ALPHABET_SIZE = 256,    // byte-level input
    parameter PATTERN_COUNT = 512,    // max patterns in table
    parameter STATE_WIDTH   = 10      // log2(NUM_STATES)
)(
    input  wire        clk,
    input  wire        rst_n,

    // Byte-stream input from MAC/TEMAC
    input  wire [7:0]  byte_in,
    input  wire        byte_valid,
    input  wire        frame_start,   // pulse: new Ethernet frame
    input  wire        frame_end,     // pulse: frame done

    // Match output
    output reg         match_found,
    output reg [9:0]   match_pattern_id,  // which pattern hit
    output reg [15:0]  match_offset,      // byte offset in frame

    // SRAM interface (for goto/fail/output tables too large for BRAM)
    output reg  [17:0] sram_addr,
    inout  wire [15:0] sram_data,
    output reg         sram_we_n,
    output reg         sram_oe_n,
    output reg         sram_ce_n
);

    // ----------------------------------------------------------
    // Internal state
    // ----------------------------------------------------------
    reg [STATE_WIDTH-1:0] current_state;
    reg [15:0]            byte_offset;
    reg                   sram_drive;
    reg [15:0]            sram_data_out;

    assign sram_data = sram_drive ? sram_data_out : 16'hZZZZ;

    // ----------------------------------------------------------
    // Goto table: stored in BRAM for single-cycle lookup
    // goto_table[state][byte] -> next_state
    // For 1024 states x 256 chars this is 256KB — too large for
    // on-chip BRAM alone; hot paths cached, cold spills to SRAM.
    // For initial prototype: reduced to 256 states fits in BRAM.
    // ----------------------------------------------------------
    // BRAM instantiation placeholder (Xilinx XPM or manual RAMB36)
    // Replace with xpm_memory_spram or RAMB36E1 primitive in Vivado
    reg [STATE_WIDTH-1:0] goto_bram [0:255][0:255];  // 256 states x 256 chars
    reg [STATE_WIDTH-1:0] fail_table [0:255];         // failure links
    reg                   output_table [0:255];       // 1 = accepting state
    reg [9:0]             output_id [0:255];          // pattern ID at accepting state

    // ----------------------------------------------------------
    // Main FSM
    // ----------------------------------------------------------
    always @(posedge clk or negedge rst_n) begin
        if (!rst_n) begin
            current_state    <= 0;
            byte_offset      <= 0;
            match_found      <= 0;
            match_pattern_id <= 0;
            match_offset     <= 0;
            sram_we_n        <= 1;
            sram_oe_n        <= 1;
            sram_ce_n        <= 1;
            sram_drive       <= 0;
        end else begin
            match_found <= 0;  // default: deassert each cycle

            if (frame_start) begin
                current_state <= 0;
                byte_offset   <= 0;
            end else if (byte_valid) begin
                // Follow goto link
                current_state <= goto_bram[current_state][byte_in];
                byte_offset   <= byte_offset + 1;

                // Check for match at new state
                if (output_table[goto_bram[current_state][byte_in]]) begin
                    match_found      <= 1;
                    match_pattern_id <= output_id[goto_bram[current_state][byte_in]];
                    match_offset     <= byte_offset;
                end
            end
        end
    end

    // ----------------------------------------------------------
    // NOTE: goto_bram, fail_table, output_table, output_id are
    // loaded at configuration time by MicroBlaze over the AXI
    // local bus from the nightly-updated threat pattern table.
    // A separate axi_table_loader.v module handles this write path.
    // ----------------------------------------------------------

endmodule

sim/tb_aho_corasick.v
`timescale 1ns/1ps

module tb_aho_corasick;

    reg        clk         = 0;
    reg        rst_n       = 0;
    reg [7:0]  byte_in     = 0;
    reg        byte_valid  = 0;
    reg        frame_start = 0;
    reg        frame_end   = 0;

    wire        match_found;
    wire [9:0]  match_pattern_id;
    wire [15:0] match_offset;

    wire [17:0] sram_addr;
    wire [15:0] sram_data;
    wire        sram_we_n, sram_oe_n, sram_ce_n;
    assign sram_data = 16'hZZZZ;  // not exercised by this test

    aho_corasick u_dut (
        .clk              (clk),
        .rst_n            (rst_n),
        .byte_in          (byte_in),
        .byte_valid       (byte_valid),
        .frame_start      (frame_start),
        .frame_end        (frame_end),
        .match_found      (match_found),
        .match_pattern_id (match_pattern_id),
        .match_offset     (match_offset),
        .sram_addr        (sram_addr),
        .sram_data        (sram_data),
        .sram_we_n        (sram_we_n),
        .sram_oe_n        (sram_oe_n),
        .sram_ce_n        (sram_ce_n)
    );

    always #4 clk = ~clk;  // 125 MHz

    initial begin
        $dumpfile("tb_aho_corasick.vcd");
        $dumpvars(0, tb_aho_corasick);
    end

    // Load the completed DFA tables generated by build_ac_table.py
    integer i, j;
    reg [9:0] goto_flat [0:255*256-1];  // flattened temp buffer
    initial begin
        $readmemh("goto_table.hex", goto_flat);
        for (i = 0; i < 256; i = i + 1) begin
            for (j = 0; j < 256; j = j + 1) begin
                u_dut.goto_bram[i][j] = goto_flat[i*256 + j];
            end
        end
        $readmemh("output_table.hex", u_dut.output_table);
        $readmemh("output_id.hex", u_dut.output_id);
        $display("DEBUG: Table Load Complete");
    end

    task send_byte;
        input [7:0] b;
        begin
            @(posedge clk);
            byte_in    <= b;
            byte_valid <= 1;
            @(posedge clk);
            byte_valid <= 0;
        end
    endtask

    task send_string;
        input [8*32-1:0] str;   // up to 32 ASCII chars, packed
        input integer len;
        integer k;
        begin
            for (k = 0; k < len; k = k + 1) begin
                send_byte(str[8*(len-1-k) +: 8]);
            end
        end
    endtask

    initial begin
        $display("DEBUG: stimulus block started");
        rst_n = 0;
        repeat(4) @(posedge clk);
        rst_n = 1;
        repeat(2) @(posedge clk);

        // -------------------------------------------------------
        // TEST 1: exact match on "evil"
        // -------------------------------------------------------
        $display("--- TEST 1: \"evil\" ---");
        @(posedge clk); frame_start <= 1; @(posedge clk); frame_start <= 0;
        send_string("evil", 4);
        @(posedge clk); frame_end <= 1; @(posedge clk); frame_end <= 0;
        repeat(2) @(posedge clk);

        // -------------------------------------------------------
        // TEST 2: "scam" embedded mid-stream, surrounded by noise
        // -------------------------------------------------------
        $display("--- TEST 2: \"xxscamxx\" ---");
        @(posedge clk); frame_start <= 1; @(posedge clk); frame_start <= 0;
        send_string("xxscamxx", 8);
        @(posedge clk); frame_end <= 1; @(posedge clk); frame_end <= 0;
        repeat(2) @(posedge clk);

        // -------------------------------------------------------
        // TEST 3: the failure-link stress case -- "scammer"
        // This should match pattern ID 2 ("scammer") at the end,
        // NOT just match "scam" and then desync.
        // -------------------------------------------------------
        $display("--- TEST 3: \"scammer\" ---");
        @(posedge clk); frame_start <= 1; @(posedge clk); frame_start <= 0;
        send_string("scammer", 7);
        @(posedge clk); frame_end <= 1; @(posedge clk); frame_end <= 0;
        repeat(2) @(posedge clk);

        // -------------------------------------------------------
        // TEST 4: no match at all -- should never assert match_found
        // -------------------------------------------------------
        $display("--- TEST 4: \"harmless\" (expect no match) ---");
        @(posedge clk); frame_start <= 1; @(posedge clk); frame_start <= 0;
        send_string("harmless", 8);
        @(posedge clk); frame_end <= 1; @(posedge clk); frame_end <= 0;
        repeat(2) @(posedge clk);

        $display("Simulation complete.");
        $finish;
    end

    // Monitor: print every match as it happens, with pattern name
    always @(posedge clk) begin
        if (match_found) begin
            case (match_pattern_id)
                10'd0: $display("  MATCH: \"evil\" at offset %0d", match_offset);
                10'd1: $display("  MATCH: \"scam\" at offset %0d", match_offset);
                10'd2: $display("  MATCH: \"scammer\" at offset %0d", match_offset);
                10'd3: $display("  MATCH: \"bad\" at offset %0d", match_offset);
                default: $display("  MATCH: unknown id %0d at offset %0d",
                                   match_pattern_id, match_offset);
            endcase
        end
    end

endmodule

sim/sim/tb_aho_corasick.vcd
$date
	Sat Jun 20 17:00:40 2026
$end
$version
	Icarus Verilog
$end
$timescale
	1ps
$end
$scope module tb_aho_corasick $end
$var wire 1 ! sram_we_n $end
$var wire 1 " sram_oe_n $end
$var wire 16 # sram_data [15:0] $end
$var wire 1 $ sram_ce_n $end
$var wire 18 % sram_addr [17:0] $end
$var wire 10 & match_pattern_id [9:0] $end
$var wire 16 ' match_offset [15:0] $end
$var wire 1 ( match_found $end
$var reg 8 ) byte_in [7:0] $end
$var reg 1 * byte_valid $end
$var reg 1 + clk $end
$var reg 1 , frame_end $end
$var reg 1 - frame_start $end
$var reg 1 . rst_n $end
$var integer 32 / i [31:0] $end
$var integer 32 0 j [31:0] $end
$scope module u_dut $end
$var wire 8 1 byte_in [7:0] $end
$var wire 1 * byte_valid $end
$var wire 1 + clk $end
$var wire 1 , frame_end $end
$var wire 1 - frame_start $end
$var wire 1 . rst_n $end
$var wire 16 2 sram_data [15:0] $end
$var parameter 32 3 ALPHABET_SIZE $end
$var parameter 32 4 NUM_STATES $end
$var parameter 32 5 PATTERN_COUNT $end
$var parameter 32 6 STATE_WIDTH $end
$var reg 16 7 byte_offset [15:0] $end
$var reg 10 8 current_state [9:0] $end
$var reg 1 ( match_found $end
$var reg 16 9 match_offset [15:0] $end
$var reg 10 : match_pattern_id [9:0] $end
$var reg 18 ; sram_addr [17:0] $end
$var reg 1 $ sram_ce_n $end
$var reg 16 < sram_data_out [15:0] $end
$var reg 1 = sram_drive $end
$var reg 1 " sram_oe_n $end
$var reg 1 ! sram_we_n $end
$upscope $end
$scope task send_byte $end
$var reg 8 > b [7:0] $end
$upscope $end
$scope task send_string $end
$var reg 256 ? str [255:0] $end
$var integer 32 @ k [31:0] $end
$var integer 32 A len [31:0] $end
$upscope $end
$upscope $end
$enddefinitions $end
$comment Show the parameter values. $end
$dumpall
b1010 6
b1000000000 5
b10000000000 4
b100000000 3
$end
#0
$dumpvars
bx A
bx @
bx ?
bx >
0=
bx <
bx ;
b0 :
b0 9
b0 8
b0 7
bz 2
b0 1
b100000000 0
b100000000 /
0.
0-
0,
0+
0*
b0 )
0(
b0 '
b0 &
bx %
1$
bz #
1"
1!
$end
#4000
1+
#8000
0+
#12000
1+
#16000
0+
#20000
1+
#24000
0+
#28000
1.
1+
#32000
0+
#36000
1+
#40000
0+
#44000
1+
#48000
0+
#52000
1-
1+
#56000
0+
#60000
0-
b1100101 >
b0 @
b100 A
b1100101011101100110100101101100 ?
1+
#64000
0+
#68000
1*
b1100101 )
b1100101 1
1+
#72000
0+
#76000
b1 7
b1 8
0*
b1110110 >
b1 @
1+
#80000
0+
#84000
1*
b1110110 )
b1110110 1
1+
#88000
0+
#92000
b10 7
b10 8
0*
b1101001 >
b10 @
1+
#96000
0+
#100000
1*
b1101001 )
b1101001 1
1+
#104000
0+
#108000
b11 7
b11 8
0*
b1101100 >
b11 @
1+
#112000
0+
#116000
1*
b1101100 )
b1101100 1
1+
#120000
0+
#124000
b11 '
b11 9
1(
b100 7
b100 8
0*
b100 @
1+
#128000
0+
#132000
0(
1,
1+
#136000
0+
#140000
0,
1+
#144000
0+
#148000
1+
#152000
0+
#156000
1+
#160000
0+
#164000
1-
1+
#168000
0+
#172000
b0 7
b0 8
0-
b1111000 >
b0 @
b1000 A
b111100001111000011100110110001101100001011011010111100001111000 ?
1+
#176000
0+
#180000
1*
b1111000 )
b1111000 1
1+
#184000
0+
#188000
b1 7
0*
b1 @
1+
#192000
0+
#196000
1*
1+
#200000
0+
#204000
b10 7
0*
b1110011 >
b10 @
1+
#208000
0+
#212000
1*
b1110011 )
b1110011 1
1+
#216000
0+
#220000
b11 7
b101 8
0*
b1100011 >
b11 @
1+
#224000
0+
#228000
1*
b1100011 )
b1100011 1
1+
#232000
0+
#236000
b100 7
b110 8
0*
b1100001 >
b100 @
1+
#240000
0+
#244000
1*
b1100001 )
b1100001 1
1+
#248000
0+
#252000
b101 7
b111 8
0*
b1101101 >
b101 @
1+
#256000
0+
#260000
1*
b1101101 )
b1101101 1
1+
#264000
0+
#268000
b101 '
b101 9
b1 &
b1 :
1(
b110 7
b1000 8
0*
b1111000 >
b110 @
1+
#272000
0+
#276000
0(
1*
b1111000 )
b1111000 1
1+
#280000
0+
#284000
b111 7
b0 8
0*
b111 @
1+
#288000
0+
#292000
1*
1+
#296000
0+
#300000
b1000 7
0*
b1000 @
1+
#304000
0+
#308000
1,
1+
#312000
0+
#316000
0,
1+
#320000
0+
#324000
1+
#328000
0+
#332000
1+
#336000
0+
#340000
1-
1+
#344000
0+
#348000
b0 7
0-
b1110011 >
b0 @
b111 A
b1110011011000110110000101101101011011010110010101110010 ?
1+
#352000
0+
#356000
1*
b1110011 )
b1110011 1
1+
#360000
0+
#364000
b1 7
b101 8
0*
b1100011 >
b1 @
1+
#368000
0+
#372000
1*
b1100011 )
b1100011 1
1+
#376000
0+
#380000
b10 7
b110 8
0*
b1100001 >
b10 @
1+
#384000
0+
#388000
1*
b1100001 )
b1100001 1
1+
#392000
0+
#396000
b11 7
b111 8
0*
b1101101 >
b11 @
1+
#400000
0+
#404000
1*
b1101101 )
b1101101 1
1+
#408000
0+
#412000
b11 '
b11 9
1(
b100 7
b1000 8
0*
b100 @
1+
#416000
0+
#420000
0(
1*
1+
#424000
0+
#428000
b101 7
b1001 8
0*
b1100101 >
b101 @
1+
#432000
0+
#436000
1*
b1100101 )
b1100101 1
1+
#440000
0+
#444000
b110 7
b1010 8
0*
b1110010 >
b110 @
1+
#448000
0+
#452000
1*
b1110010 )
b1110010 1
1+
#456000
0+
#460000
b110 '
b110 9
b10 &
b10 :
1(
b111 7
b1011 8
0*
b111 @
1+
#464000
0+
#468000
0(
1,
1+
#472000
0+
#476000
0,
1+
#480000
0+
#484000
1+
#488000
0+
#492000
1+
#496000
0+
#500000
1-
1+
#504000
0+
#508000
b0 7
b0 8
0-
b1101000 >
b0 @
b1000 A
b110100001100001011100100110110101101100011001010111001101110011 ?
1+
#512000
0+
#516000
1*
b1101000 )
b1101000 1
1+
#520000
0+
#524000
b1 7
0*
b1100001 >
b1 @
1+
#528000
0+
#532000
1*
b1100001 )
b1100001 1
1+
#536000
0+
#540000
b10 7
0*
b1110010 >
b10 @
1+
#544000
0+
#548000
1*
b1110010 )
b1110010 1
1+
#552000
0+
#556000
b11 7
0*
b1101101 >
b11 @
1+
#560000
0+
#564000
1*
b1101101 )
b1101101 1
1+
#568000
0+
#572000
b100 7
0*
b1101100 >
b100 @
1+
#576000
0+
#580000
1*
b1101100 )
b1101100 1
1+
#584000
0+
#588000
b101 7
0*
b1100101 >
b101 @
1+
#592000
0+
#596000
1*
b1100101 )
b1100101 1
1+
#600000
0+
#604000
b110 7
b1 8
0*
b1110011 >
b110 @
1+
#608000
0+
#612000
1*
b1110011 )
b1110011 1
1+
#616000
0+
#620000
b111 7
b101 8
0*
b111 @
1+
#624000
0+
#628000
1*
1+
#632000
0+
#636000
b1000 7
0*
b1000 @
1+
#640000
0+
#644000
1,
1+
#648000
0+
#652000
0,
1+
