sim/dns_parser.v
// ============================================================
// HASS - DNS Protocol Parser + Sinkhole Engine
// Decodes DNS queries per RFC 1035 (including compressed labels)
// Flags: DNS rebinding, NXDOMAIN flood, known-bad domain match
// Sinkhole: forges DNS response pointing to 192.168.254.1
// Target: Artix-7 XC7A100T @ 125 MHz
// ============================================================

module dns_parser (
    input  wire        clk,
    input  wire        rst_n,

    // Byte stream from TEMAC (UDP payload only — parser assumes
    // Ethernet/IP/UDP headers already stripped by hass_top)
    input  wire [7:0]  byte_in,
    input  wire        byte_valid,
    input  wire        frame_start,
    input  wire        frame_end,

    // Signal from Aho-Corasick: domain in current query is on no-fly list
    input  wire        ac_match,

    // Alert and sinkhole outputs
    output reg         dns_alert,        // any DNS threat flag
    output reg         sinkhole_active,  // tell TEMAC to forge response
    output reg [31:0]  sinkhole_ip,      // always 192.168.254.1

    // NXDOMAIN flood tracking (counts per frame window)
    output reg [7:0]   nxdomain_count
);

    // ----------------------------------------------------------
    // Sinkhole IP is fixed — MicroBlaze warning page lives here
    // ----------------------------------------------------------
    localparam SINKHOLE_ADDR = 32'hC0A8FE01;  // 192.168.254.1

    // ----------------------------------------------------------
    // RFC 1035 DNS header offsets (all fields big-endian)
    // Byte 0-1  : Transaction ID
    // Byte 2-3  : Flags (QR, Opcode, AA, TC, RD, RA, Z, RCODE)
    // Byte 4-5  : QDCOUNT
    // Byte 6-7  : ANCOUNT
    // Byte 8-9  : NSCOUNT
    // Byte 10-11: ARCOUNT
    // Byte 12+  : Question section (QNAME, QTYPE, QCLASS)
    // ----------------------------------------------------------

    // Parser FSM states
    localparam S_IDLE       = 4'd0;
    localparam S_HDR        = 4'd1;   // consuming 12-byte header
    localparam S_QNAME      = 4'd2;   // reading label sequence
    localparam S_LABEL_DATA = 4'd3;   // consuming label bytes
    localparam S_QTYPE_HI   = 4'd4;   // QTYPE high byte
    localparam S_QTYPE_LO   = 4'd5;   // QTYPE low byte
    localparam S_QCLASS_HI  = 4'd6;
    localparam S_QCLASS_LO  = 4'd7;
    localparam S_ANSWER     = 4'd8;   // scanning answer section
    localparam S_RDATA      = 4'd9;   // reading RDATA (check for RFC-1918)
    localparam S_DONE       = 4'd10;

    reg [3:0]  state;
    reg [3:0]  byte_idx;       // position within current header field
    reg [7:0]  label_len;      // current label length byte
    reg [7:0]  label_remaining;// bytes left in current label
    reg [7:0]  hdr_count;      // counts through 12-byte header

    // Extracted header fields
    reg [15:0] tx_id;
    reg [15:0] flags;
    reg [15:0] qdcount;
    reg [15:0] ancount;
    reg [3:0]  rcode;          // response code (NXDOMAIN = 3)
    reg        is_response;    // QR bit

    // Answer section RDATA capture (for rebinding check)
    reg [31:0] rdata_ip;
    reg [7:0]  rdata_byte_idx;

    // NXDOMAIN flood: count responses with RCODE=3 in a time window
    // Window = 65536 clock cycles (~524us @ 125MHz), reset on overflow
    reg [15:0] nxdomain_window_timer;
    localparam NXDOMAIN_THRESH = 8'd10;   // >10 NXDOMAINs per window = flood

    // ----------------------------------------------------------
    // RFC-1918 check: is an IP in a private range?
    // 10.0.0.0/8, 172.16.0.0/12, 192.168.0.0/16
    // ----------------------------------------------------------
    function is_rfc1918;
        input [31:0] ip;
        begin
            is_rfc1918 = (ip[31:24] == 8'd10) ||
                         (ip[31:24] == 8'd172 && ip[23:20] == 4'd1) ||
                         (ip[31:24] == 8'd192 && ip[23:16] == 8'd168);
        end
    endfunction

    // ----------------------------------------------------------
    // Main parser FSM
    // ----------------------------------------------------------
    always @(posedge clk or negedge rst_n) begin
        if (!rst_n) begin
            state             <= S_IDLE;
            byte_idx          <= 0;
            hdr_count         <= 0;
            label_len         <= 0;
            label_remaining   <= 0;
            tx_id             <= 0;
            flags             <= 0;
            qdcount           <= 0;
            ancount           <= 0;
            rcode             <= 0;
            is_response       <= 0;
            rdata_ip          <= 0;
            rdata_byte_idx    <= 0;
            dns_alert         <= 0;
            sinkhole_active   <= 0;
            sinkhole_ip       <= SINKHOLE_ADDR;
            nxdomain_count    <= 0;
            nxdomain_window_timer <= 0;
        end else begin

            // Default: deassert pulse signals each cycle
            dns_alert       <= 0;
            sinkhole_active <= 0;

            // NXDOMAIN flood window timer — free-running
            if (nxdomain_window_timer == 16'hFFFF) begin
                nxdomain_window_timer <= 0;
                nxdomain_count        <= 0;  // reset count each window
            end else begin
                nxdomain_window_timer <= nxdomain_window_timer + 1;
            end

            if (frame_start) begin
                state      <= S_HDR;
                hdr_count  <= 0;
                byte_idx   <= 0;
            end else if (byte_valid) begin
                case (state)

                    // ------------------------------------------
                    // Consume 12-byte DNS header
                    // ------------------------------------------
                    S_HDR: begin
                        case (hdr_count)
                            8'd0:  tx_id[15:8]  <= byte_in;
                            8'd1:  tx_id[7:0]   <= byte_in;
                            8'd2: begin
                                flags[15:8] <= byte_in;
                                is_response <= byte_in[7]; // QR bit
                            end
                            8'd3: begin
                                flags[7:0] <= byte_in;
                                rcode      <= byte_in[3:0];
                            end
                            8'd4:  qdcount[15:8] <= byte_in;
                            8'd5:  qdcount[7:0]  <= byte_in;
                            8'd6:  ancount[15:8] <= byte_in;
                            8'd7:  ancount[7:0]  <= byte_in;
                            // NSCOUNT and ARCOUNT ignored
                        endcase

                        if (hdr_count == 8'd11) begin
                            hdr_count <= 0;
                            // Check for NXDOMAIN flood on response packets
                            if (is_response && rcode == 4'd3) begin
                                nxdomain_count <= nxdomain_count + 1;
                                if (nxdomain_count >= NXDOMAIN_THRESH) begin
                                    dns_alert <= 1;
                                end
                            end
                            state <= S_QNAME;
                        end else begin
                            hdr_count <= hdr_count + 1;
                        end
                    end

                    // ------------------------------------------
                    // QNAME: sequence of length-prefixed labels
                    // terminated by 0x00 or a compression pointer
                    // (top two bits = 11 signals pointer per RFC 1035)
                    // ------------------------------------------
                    S_QNAME: begin
                        if (byte_in == 8'h00) begin
                            // Root label — end of QNAME
                            state <= S_QTYPE_HI;
                        end else if (byte_in[7:6] == 2'b11) begin
                            // Compression pointer — skip one more byte
                            // then move to QTYPE (we don't follow pointers
                            // in hardware; AC engine handles domain matching)
                            label_remaining <= 1;
                            state           <= S_LABEL_DATA;
                            // After label_data drains, go to QTYPE
                        end else begin
                            // Normal label: byte_in is length
                            label_len       <= byte_in;
                            label_remaining <= byte_in;
                            state           <= S_LABEL_DATA;
                        end
                    end

                    S_LABEL_DATA: begin
                        if (label_remaining == 1) begin
                            state <= S_QNAME;  // back to read next length byte
                        end else begin
                            label_remaining <= label_remaining - 1;
                        end
                    end

                    S_QTYPE_HI:  state <= S_QTYPE_LO;   // ignore QTYPE value
                    S_QTYPE_LO:  state <= S_QCLASS_HI;
                    S_QCLASS_HI: state <= S_QCLASS_LO;
                    S_QCLASS_LO: begin
                        // Done with question section
                        // If AC engine matched this domain, sinkhole it
                        if (ac_match) begin
                            dns_alert       <= 1;
                            sinkhole_active <= 1;
                            sinkhole_ip     <= SINKHOLE_ADDR;
                        end
                        // If this is a response, scan answer section
                        // for DNS rebinding (public name -> RFC-1918 IP)
                        if (is_response && ancount > 0) begin
                            rdata_byte_idx <= 0;
                            state          <= S_ANSWER;
                        end else begin
                            state <= S_DONE;
                        end
                    end

                    // ------------------------------------------
                    // Answer section: skip NAME (compressed, 2 bytes)
                    // TYPE (2), CLASS (2), TTL (4), RDLENGTH (2)
                    // then read RDATA for A-record rebinding check
                    // Total header before RDATA = 12 bytes
                    // ------------------------------------------
                    S_ANSWER: begin
                        rdata_byte_idx <= rdata_byte_idx + 1;
                        if (rdata_byte_idx == 8'd11) begin
                            // About to read RDATA — reset for IP capture
                            rdata_byte_idx <= 0;
                            rdata_ip       <= 0;
                            state          <= S_RDATA;
                        end
                    end

                    // ------------------------------------------
                    // Capture 4-byte A record RDATA and check
                    // for RFC-1918 address (DNS rebinding attack)
                    // ------------------------------------------
                    S_RDATA: begin
                        case (rdata_byte_idx)
                            8'd0: rdata_ip[31:24] <= byte_in;
                            8'd1: rdata_ip[23:16] <= byte_in;
                            8'd2: rdata_ip[15:8]  <= byte_in;
                            8'd3: begin
                                rdata_ip[7:0] <= byte_in;
                                // Check complete IP for rebinding
                                if (is_rfc1918({rdata_ip[31:8], byte_in})) begin
                                    dns_alert <= 1;
                                end
                                state <= S_DONE;
                            end
                        endcase
                        rdata_byte_idx <= rdata_byte_idx + 1;
                    end

                    S_DONE: begin
                        // Hold until frame_end resets via frame_start
                    end

                    default: state <= S_IDLE;
                endcase
            end
        end
    end

endmodule

sim/tb_dns_parser.v
`timescale 1ns/1ps

module tb_dns_parser;

    //-------------------------------------------------------
    // DUT Inputs
    //-------------------------------------------------------
    reg         clk         = 0;
    reg         rst_n       = 0;

    reg [7:0]   byte_in     = 0;
    reg         byte_valid  = 0;
    reg         frame_start = 0;
    reg         frame_end   = 0;

    reg         ac_match    = 0;


    //-------------------------------------------------------
    // DUT Outputs
    //-------------------------------------------------------

    wire        dns_alert;
    wire        sinkhole_active;
    wire [31:0] sinkhole_ip;
    wire [7:0]  nxdomain_count;



    //-------------------------------------------------------
    // Instantiate DUT
    //-------------------------------------------------------

    dns_parser u_dut (

        .clk(clk),
        .rst_n(rst_n),

        .byte_in(byte_in),
        .byte_valid(byte_valid),

        .frame_start(frame_start),
        .frame_end(frame_end),

        .ac_match(ac_match),

        .dns_alert(dns_alert),
        .sinkhole_active(sinkhole_active),
        .sinkhole_ip(sinkhole_ip),

        .nxdomain_count(nxdomain_count)

    );


    //-------------------------------------------------------
    // 125 MHz clock
    //-------------------------------------------------------

    always #4 clk = ~clk;



    //-------------------------------------------------------
    // VCD
    //-------------------------------------------------------

    initial begin

        $dumpfile("tb_dns_parser.vcd");
        $dumpvars(0,tb_dns_parser);

    end



    //-------------------------------------------------------
    // Send one byte
    //-------------------------------------------------------

    task send_byte;

        input [7:0] b;

        begin

            @(posedge clk);

            byte_in <= b;
            byte_valid <= 1;

            @(posedge clk);

            byte_valid <= 0;

        end

    endtask



    //-------------------------------------------------------
    // DNS query helper
    //-------------------------------------------------------

    task send_query;

        integer i;

        begin

            @(posedge clk);
            frame_start <= 1;

            @(posedge clk);
            frame_start <= 0;


            //---------------------------------------
            // Header
            //---------------------------------------

            send_byte(8'h12);
            send_byte(8'h34);

            send_byte(8'h01);
            send_byte(8'h00);

            send_byte(8'h00);
            send_byte(8'h01);

            send_byte(8'h00);
            send_byte(8'h00);

            send_byte(8'h00);
            send_byte(8'h00);

            send_byte(8'h00);
            send_byte(8'h00);



            //---------------------------------------
            // www.google.com
            //---------------------------------------

            send_byte(8'd3);
            send_byte("w");
            send_byte("w");
            send_byte("w");


            send_byte(8'd6);
            send_byte("g");
            send_byte("o");
            send_byte("o");
            send_byte("g");
            send_byte("l");
            send_byte("e");


            send_byte(8'd3);
            send_byte("c");
            send_byte("o");
            send_byte("m");


            send_byte(8'h00);



            //---------------------------------------
            // A record
            //---------------------------------------

            send_byte(8'h00);
            send_byte(8'h01);


            send_byte(8'h00);
            send_byte(8'h01);



            @(posedge clk);

            frame_end <= 1;

            @(posedge clk);

            frame_end <= 0;

        end

    endtask




    //-------------------------------------------------------
    // NXDOMAIN response helper
    //-------------------------------------------------------

    task send_nxdomain;

        begin

            @(posedge clk);
            frame_start<=1;

            @(posedge clk);
            frame_start<=0;



            send_byte(8'h12);
            send_byte(8'h34);


            // QR=1
            send_byte(8'h81);

            // RCODE=3
            send_byte(8'h83);



            repeat(8)
                send_byte(8'h00);



            send_byte(8'h00);



            @(posedge clk);

            frame_end<=1;

            @(posedge clk);

            frame_end<=0;

        end

    endtask




    //-------------------------------------------------------
    // Rebinding helper
    //-------------------------------------------------------

    task send_rebinding_response;

        integer i;

        begin

            @(posedge clk);
            frame_start<=1;

            @(posedge clk);
            frame_start<=0;



            //------------------------------------
            // DNS header
            //------------------------------------

            send_byte(8'h12);
            send_byte(8'h34);


            send_byte(8'h81);
            send_byte(8'h80);



            send_byte(8'h00);
            send_byte(8'h01);



            send_byte(8'h00);
            send_byte(8'h01);



            send_byte(8'h00);
            send_byte(8'h00);

            send_byte(8'h00);
            send_byte(8'h00);



            //------------------------------------
            // minimal qname
            //------------------------------------

            send_byte(8'h00);

            send_byte(8'h00);
            send_byte(8'h01);

            send_byte(8'h00);
            send_byte(8'h01);



            //------------------------------------
            // answer header
            //------------------------------------

            for(i=0;i<12;i=i+1)
                send_byte(8'h00);



            //------------------------------------
            // RFC1918 address
            //------------------------------------

            send_byte(8'd192);
            send_byte(8'd168);
            send_byte(8'd1);
            send_byte(8'd5);



            @(posedge clk);

            frame_end<=1;

            @(posedge clk);

            frame_end<=0;

        end

    endtask




    //-------------------------------------------------------
    // Main stimulus
    //-------------------------------------------------------

    integer k;


    initial begin


        $display("DNS Parser TB Started");


        rst_n=0;

        repeat(4)
            @(posedge clk);

        rst_n=1;

        repeat(2)
            @(posedge clk);



        //----------------------------------------------------
        // TEST 1
        //----------------------------------------------------

        $display("--------------------------------");
        $display("TEST1 Normal query");
        $display("--------------------------------");

        send_query();

        repeat(10) @(posedge clk);

        $display("alert=%b",dns_alert);



        //----------------------------------------------------
        // TEST 2
        //----------------------------------------------------

        $display("--------------------------------");
        $display("TEST2 AC match");
        $display("--------------------------------");


        ac_match=1;

        send_query();

        repeat(10)
            @(posedge clk);

        ac_match=0;


        $display("alert=%b",dns_alert);
        $display("sinkhole=%b",sinkhole_active);
        $display("ip=%h",sinkhole_ip);



        //----------------------------------------------------
        // TEST 3
        //----------------------------------------------------

        $display("--------------------------------");
        $display("TEST3 NXDOMAIN");
        $display("--------------------------------");


        send_nxdomain();

        repeat(10)
            @(posedge clk);


        $display("count=%d",
                    nxdomain_count);




        //----------------------------------------------------
        // TEST 4
        //----------------------------------------------------

        $display("--------------------------------");
        $display("TEST4 NXDOMAIN flood");
        $display("--------------------------------");


        for(k=0;k<12;k=k+1)
            send_nxdomain();


        repeat(20)
            @(posedge clk);


        $display("count=%d",
                    nxdomain_count);

        $display("alert=%b",
                    dns_alert);



        //----------------------------------------------------
        // TEST 5
        //----------------------------------------------------

        $display("--------------------------------");
        $display("TEST5 Rebinding");
        $display("--------------------------------");


        send_rebinding_response();


        repeat(20)
            @(posedge clk);



        $display("alert=%b",
                    dns_alert);




        //----------------------------------------------------
        // TEST 6
        //----------------------------------------------------

        $display("--------------------------------");
        $display("TEST6 Empty frame");
        $display("--------------------------------");


        @(posedge clk);
        frame_start<=1;

        @(posedge clk);
        frame_start<=0;


        @(posedge clk);
        frame_end<=1;

        @(posedge clk);
        frame_end<=0;


        repeat(10)
            @(posedge clk);



        $display("Simulation complete");

        $finish;


    end

endmodule

sim/tb_dns_parser.vcd
$date
	Sun Jun 21 12:50:13 2026
$end
$version
	Icarus Verilog
$end
$timescale
	1ps
$end
$scope module tb_dns_parser $end
$var wire 32 ! sinkhole_ip [31:0] $end
$var wire 1 " sinkhole_active $end
$var wire 8 # nxdomain_count [7:0] $end
$var wire 1 $ dns_alert $end
$var reg 1 % ac_match $end
$var reg 8 & byte_in [7:0] $end
$var reg 1 ' byte_valid $end
$var reg 1 ( clk $end
$var reg 1 ) frame_end $end
$var reg 1 * frame_start $end
$var reg 1 + rst_n $end
$var integer 32 , k [31:0] $end
$scope module u_dut $end
$var wire 1 % ac_match $end
$var wire 8 - byte_in [7:0] $end
$var wire 1 ' byte_valid $end
$var wire 1 ( clk $end
$var wire 1 ) frame_end $end
$var wire 1 * frame_start $end
$var wire 1 + rst_n $end
$var parameter 8 . NXDOMAIN_THRESH $end
$var parameter 32 / SINKHOLE_ADDR $end
$var parameter 4 0 S_ANSWER $end
$var parameter 4 1 S_DONE $end
$var parameter 4 2 S_HDR $end
$var parameter 4 3 S_IDLE $end
$var parameter 4 4 S_LABEL_DATA $end
$var parameter 4 5 S_QCLASS_HI $end
$var parameter 4 6 S_QCLASS_LO $end
$var parameter 4 7 S_QNAME $end
$var parameter 4 8 S_QTYPE_HI $end
$var parameter 4 9 S_QTYPE_LO $end
$var parameter 4 : S_RDATA $end
$var reg 16 ; ancount [15:0] $end
$var reg 4 < byte_idx [3:0] $end
$var reg 1 $ dns_alert $end
$var reg 16 = flags [15:0] $end
$var reg 8 > hdr_count [7:0] $end
$var reg 1 ? is_response $end
$var reg 8 @ label_len [7:0] $end
$var reg 8 A label_remaining [7:0] $end
$var reg 8 B nxdomain_count [7:0] $end
$var reg 16 C nxdomain_window_timer [15:0] $end
$var reg 16 D qdcount [15:0] $end
$var reg 4 E rcode [3:0] $end
$var reg 8 F rdata_byte_idx [7:0] $end
$var reg 32 G rdata_ip [31:0] $end
$var reg 1 " sinkhole_active $end
$var reg 32 H sinkhole_ip [31:0] $end
$var reg 4 I state [3:0] $end
$var reg 16 J tx_id [15:0] $end
$scope function is_rfc1918 $end
$var reg 32 K ip [31:0] $end
$upscope $end
$upscope $end
$scope task end_frame $end
$upscope $end
$scope task send_byte $end
$var reg 8 L b [7:0] $end
$upscope $end
$scope task send_nxdomain_response $end
$upscope $end
$scope task send_query_evilcom $end
$upscope $end
$scope task send_rebinding_response $end
$upscope $end
$scope task start_frame $end
$upscope $end
$upscope $end
$enddefinitions $end
$comment Show the parameter values. $end
$dumpall
b1001 :
b101 9
b100 8
b10 7
b111 6
b110 5
b11 4
b0 3
b1 2
b1010 1
b1000 0
b11000000101010001111111000000001 /
b1010 .
$end
#0
$dumpvars
bx L
bx K
b0 J
b0 I
b11000000101010001111111000000001 H
b0 G
b0 F
b0 E
b0 D
b0 C
b0 B
b0 A
b0 @
0?
b0 >
b0 =
b0 <
b0 ;
b0 -
bx ,
0+
0*
0)
0(
0'
b0 &
0%
0$
b0 #
0"
b11000000101010001111111000000001 !
$end
#4000
1(
#8000
0(
#12000
1(
#16000
0(
#20000
1(
#24000
0(
#28000
b1 C
1+
1(
#32000
0(
#36000
b10 C
1(
#40000
0(
#44000
b11 C
1(
#48000
0(
#52000
b100 C
1*
1(
#56000
0(
#60000
b1 I
b101 C
0*
b10010 L
1%
1(
#64000
0(
#68000
b110 C
1'
b10010 &
b10010 -
1(
#72000
0(
#76000
b1 >
b1001000000000 J
b111 C
0'
b110100 L
1(
#80000
0(
#84000
b1000 C
1'
b110100 &
b110100 -
1(
#88000
0(
#92000
b10 >
b1001000110100 J
b1001 C
0'
b1 L
1(
#96000
0(
#100000
b1010 C
1'
b1 &
b1 -
1(
#104000
0(
#108000
b11 >
b100000000 =
b1011 C
0'
b0 L
1(
#112000
0(
#116000
b1100 C
1'
b0 &
b0 -
1(
#120000
0(
#124000
b100 >
b1101 C
0'
1(
#128000
0(
#132000
b1110 C
1'
1(
#136000
0(
#140000
b101 >
b1111 C
0'
b1 L
1(
#144000
0(
#148000
b10000 C
1'
b1 &
b1 -
1(
#152000
0(
#156000
b110 >
b1 D
b10001 C
0'
b0 L
1(
#160000
0(
#164000
b10010 C
1'
b0 &
b0 -
1(
#168000
0(
#172000
b111 >
b10011 C
0'
1(
#176000
0(
#180000
b10100 C
1'
1(
#184000
0(
#188000
b1000 >
b10101 C
0'
1(
#192000
0(
#196000
b10110 C
1'
1(
#200000
0(
#204000
b1001 >
b10111 C
0'
1(
#208000
0(
#212000
b11000 C
1'
1(
#216000
0(
#220000
b1010 >
b11001 C
0'
1(
#224000
0(
#228000
b11010 C
1'
1(
#232000
0(
#236000
b1011 >
b11011 C
0'
1(
#240000
0(
#244000
b11100 C
1'
1(
#248000
0(
#252000
b10 I
b0 >
b11101 C
0'
b100 L
1(
#256000
0(
#260000
b11110 C
1'
b100 &
b100 -
1(
#264000
0(
#268000
b11 I
b100 A
b100 @
b11111 C
0'
b1100101 L
1(
#272000
0(
#276000
b100000 C
1'
b1100101 &
b1100101 -
1(
#280000
0(
#284000
b11 A
b100001 C
0'
b1110110 L
1(
#288000
0(
#292000
b100010 C
1'
b1110110 &
b1110110 -
1(
#296000
0(
#300000
b10 A
b100011 C
0'
b1101001 L
1(
#304000
0(
#308000
b100100 C
1'
b1101001 &
b1101001 -
1(
#312000
0(
#316000
b1 A
b100101 C
0'
b1101100 L
1(
#320000
0(
#324000
b100110 C
1'
b1101100 &
b1101100 -
1(
#328000
0(
#332000
b10 I
b100111 C
0'
b11 L
1(
#336000
0(
#340000
b101000 C
1'
b11 &
b11 -
1(
#344000
0(
#348000
b11 I
b11 A
b11 @
b101001 C
0'
b1100011 L
1(
#352000
0(
#356000
b101010 C
1'
b1100011 &
b1100011 -
1(
#360000
0(
#364000
b10 A
b101011 C
0'
b1101111 L
1(
#368000
0(
#372000
b101100 C
1'
b1101111 &
b1101111 -
1(
#376000
0(
#380000
b1 A
b101101 C
0'
b1101101 L
1(
#384000
0(
#388000
b101110 C
1'
b1101101 &
b1101101 -
1(
#392000
0(
#396000
b10 I
b101111 C
0'
b0 L
1(
#400000
0(
#404000
b110000 C
1'
b0 &
b0 -
1(
#408000
0(
#412000
b100 I
b110001 C
0'
1(
#416000
0(
#420000
b110010 C
1'
1(
#424000
0(
#428000
b101 I
b110011 C
0'
b1 L
1(
#432000
0(
#436000
b110100 C
1'
b1 &
b1 -
1(
#440000
0(
#444000
b110 I
b110101 C
0'
b0 L
1(
#448000
0(
#452000
b110110 C
1'
b0 &
b0 -
1(
#456000
0(
#460000
b111 I
b110111 C
0'
b1 L
1(
#464000
0(
#468000
b111000 C
1'
b1 &
b1 -
1(
#472000
0(
#476000
b1010 I
1"
1$
b111001 C
0'
1(
#480000
0(
#484000
b111010 C
0"
0$
1(
#488000
0(
#492000
b111011 C
1(
#496000
0(
#500000
b111100 C
1(
#504000
0(
#508000
b111101 C
0%
1(
#512000
0(
#516000
b111110 C
1)
1(
#520000
0(
#524000
b111111 C
0)
1(
#528000
0(
#532000
b1000000 C
1(
#536000
0(
#540000
b1000001 C
1(
#544000
0(
#548000
b1000010 C
1(
#552000
0(
#556000
b1000011 C
1(
#560000
0(
#564000
b1000100 C
1*
1(
#568000
0(
#572000
b1 I
b1000101 C
0*
b10010 L
1(
#576000
0(
#580000
b1000110 C
1'
b10010 &
b10010 -
1(
#584000
0(
#588000
b1 >
b1000111 C
0'
b110100 L
1(
#592000
0(
#596000
b1001000 C
1'
b110100 &
b110100 -
1(
#600000
0(
#604000
b10 >
b1001001 C
0'
b1 L
1(
#608000
0(
#612000
b1001010 C
1'
b1 &
b1 -
1(
#616000
0(
#620000
b11 >
b1001011 C
0'
b0 L
1(
#624000
0(
#628000
b1001100 C
1'
b0 &
b0 -
1(
#632000
0(
#636000
b100 >
b1001101 C
0'
1(
#640000
0(
#644000
b1001110 C
1'
1(
#648000
0(
#652000
b101 >
b1001111 C
0'
b1 L
1(
#656000
0(
#660000
b1010000 C
1'
b1 &
b1 -
1(
#664000
0(
#668000
b110 >
b1010001 C
0'
b0 L
1(
#672000
0(
#676000
b1010010 C
1'
b0 &
b0 -
1(
#680000
0(
#684000
b111 >
b1010011 C
0'
1(
#688000
0(
#692000
b1010100 C
1'
1(
#696000
0(
#700000
b1000 >
b1010101 C
0'
1(
#704000
0(
#708000
b1010110 C
1'
1(
#712000
0(
#716000
b1001 >
b1010111 C
0'
1(
#720000
0(
#724000
b1011000 C
1'
1(
#728000
0(
#732000
b1010 >
b1011001 C
0'
1(
#736000
0(
#740000
b1011010 C
1'
1(
#744000
0(
#748000
b1011 >
b1011011 C
0'
1(
#752000
0(
#756000
b1011100 C
1'
1(
#760000
0(
#764000
b10 I
b0 >
b1011101 C
0'
b100 L
1(
#768000
0(
#772000
b1011110 C
1'
b100 &
b100 -
1(
#776000
0(
#780000
b11 I
b100 A
b100 @
b1011111 C
0'
b1100101 L
1(
#784000
0(
#788000
b1100000 C
1'
b1100101 &
b1100101 -
1(
#792000
0(
#796000
b11 A
b1100001 C
0'
b1110110 L
1(
#800000
0(
#804000
b1100010 C
1'
b1110110 &
b1110110 -
1(
#808000
0(
#812000
b10 A
b1100011 C
0'
b1101001 L
1(
#816000
0(
#820000
b1100100 C
1'
b1101001 &
b1101001 -
1(
#824000
0(
#828000
b1 A
b1100101 C
0'
b1101100 L
1(
#832000
0(
#836000
b1100110 C
1'
b1101100 &
b1101100 -
1(
#840000
0(
#844000
b10 I
b1100111 C
0'
b11 L
1(
#848000
0(
#852000
b1101000 C
1'
b11 &
b11 -
1(
#856000
0(
#860000
b11 I
b11 A
b11 @
b1101001 C
0'
b1100011 L
1(
#864000
0(
#868000
b1101010 C
1'
b1100011 &
b1100011 -
1(
#872000
0(
#876000
b10 A
b1101011 C
0'
b1101111 L
1(
#880000
0(
#884000
b1101100 C
1'
b1101111 &
b1101111 -
1(
#888000
0(
#892000
b1 A
b1101101 C
0'
b1101101 L
1(
#896000
0(
#900000
b1101110 C
1'
b1101101 &
b1101101 -
1(
#904000
0(
#908000
b10 I
b1101111 C
0'
b0 L
1(
#912000
0(
#916000
b1110000 C
1'
b0 &
b0 -
1(
#920000
0(
#924000
b100 I
b1110001 C
0'
1(
#928000
0(
#932000
b1110010 C
1'
1(
#936000
0(
#940000
b101 I
b1110011 C
0'
b1 L
1(
#944000
0(
#948000
b1110100 C
1'
b1 &
b1 -
1(
#952000
0(
#956000
b110 I
b1110101 C
0'
b0 L
1(
#960000
0(
#964000
b1110110 C
1'
b0 &
b0 -
1(
#968000
0(
#972000
b111 I
b1110111 C
0'
b1 L
1(
#976000
0(
#980000
b1111000 C
1'
b1 &
b1 -
1(
#984000
0(
#988000
b1010 I
b1111001 C
0'
1(
#992000
0(
#996000
b1111010 C
1)
1(
#1000000
0(
#1004000
b1111011 C
0)
1(
#1008000
0(
#1012000
b1111100 C
1(
#1016000
0(
#1020000
b1111101 C
1(
#1024000
0(
#1028000
b1111110 C
1(
#1032000
0(
#1036000
b1111111 C
1(
#1040000
0(
#1044000
b10000000 C
1*
1(
#1048000
0(
#1052000
b1 I
b10000001 C
0*
b0 L
1(
#1056000
0(
#1060000
b10000010 C
1'
b0 &
b0 -
1(
#1064000
0(
#1068000
b1 >
b110100 J
b10000011 C
0'
1(
#1072000
0(
#1076000
b10000100 C
1'
1(
#1080000
0(
#1084000
b10 >
b0 J
b10000101 C
0'
b10000001 L
1(
#1088000
0(
#1092000
b10000110 C
1'
b10000001 &
b10000001 -
1(
#1096000
0(
#1100000
b11 >
1?
b1000000100000000 =
b10000111 C
0'
b10000000 L
1(
#1104000
0(
#1108000
b10001000 C
1'
b10000000 &
b10000000 -
1(
#1112000
0(
#1116000
b100 >
b1000000110000000 =
b10001001 C
0'
b0 L
1(
#1120000
0(
#1124000
b10001010 C
1'
b0 &
b0 -
1(
#1128000
0(
#1132000
b101 >
b10001011 C
0'
b1 L
1(
#1136000
0(
#1140000
b10001100 C
1'
b1 &
b1 -
1(
#1144000
0(
#1148000
b110 >
b10001101 C
0'
b0 L
1(
#1152000
0(
#1156000
b10001110 C
1'
b0 &
b0 -
1(
#1160000
0(
#1164000
b111 >
b10001111 C
0'
b1 L
1(
#1168000
0(
#1172000
b10010000 C
1'
b1 &
b1 -
1(
#1176000
0(
#1180000
b1000 >
b1 ;
b10010001 C
0'
b0 L
1(
#1184000
0(
#1188000
b10010010 C
1'
b0 &
b0 -
1(
#1192000
0(
#1196000
b1001 >
b10010011 C
0'
1(
#1200000
0(
#1204000
b10010100 C
1'
1(
#1208000
0(
#1212000
b1010 >
b10010101 C
0'
1(
#1216000
0(
#1220000
b10010110 C
1'
1(
#1224000
0(
#1228000
b1011 >
b10010111 C
0'
1(
#1232000
0(
#1236000
b10011000 C
1'
1(
#1240000
0(
#1244000
b10 I
b0 >
b10011001 C
0'
b1 L
1(
#1248000
0(
#1252000
b10011010 C
1'
b1 &
b1 -
1(
#1256000
0(
#1260000
b11 I
b1 @
b10011011 C
0'
b1111000 L
1(
#1264000
0(
#1268000
b10011100 C
1'
b1111000 &
b1111000 -
1(
#1272000
0(
#1276000
b10 I
b10011101 C
0'
b11 L
1(
#1280000
0(
#1284000
b10011110 C
1'
b11 &
b11 -
1(
#1288000
0(
#1292000
b11 I
b11 A
b11 @
b10011111 C
0'
b1100011 L
1(
#1296000
0(
#1300000
b10100000 C
1'
b1100011 &
b1100011 -
1(
#1304000
0(
#1308000
b10 A
b10100001 C
0'
b1101111 L
1(
#1312000
0(
#1316000
b10100010 C
1'
b1101111 &
b1101111 -
1(
#1320000
0(
#1324000
b1 A
b10100011 C
0'
b1101101 L
1(
#1328000
0(
#1332000
b10100100 C
1'
b1101101 &
b1101101 -
1(
#1336000
0(
#1340000
b10 I
b10100101 C
0'
b0 L
1(
#1344000
0(
#1348000
b10100110 C
1'
b0 &
b0 -
1(
#1352000
0(
#1356000
b100 I
b10100111 C
0'
1(
#1360000
0(
#1364000
b10101000 C
1'
1(
#1368000
0(
#1372000
b101 I
b10101001 C
0'
b1 L
1(
#1376000
0(
#1380000
b10101010 C
1'
b1 &
b1 -
1(
#1384000
0(
#1388000
b110 I
b10101011 C
0'
b0 L
1(
#1392000
0(
#1396000
b10101100 C
1'
b0 &
b0 -
1(
#1400000
0(
#1404000
b111 I
b10101101 C
0'
b1 L
1(
#1408000
0(
#1412000
b10101110 C
1'
b1 &
b1 -
1(
#1416000
0(
#1420000
b1000 I
b10101111 C
0'
b11000000 L
1(
#1424000
0(
#1428000
b10110000 C
1'
b11000000 &
b11000000 -
1(
#1432000
0(
#1436000
b1 F
b10110001 C
0'
b1100 L
1(
#1440000
0(
#1444000
b10110010 C
1'
b1100 &
b1100 -
1(
#1448000
0(
#1452000
b10 F
b10110011 C
0'
b0 L
1(
#1456000
0(
#1460000
b10110100 C
1'
b0 &
b0 -
1(
#1464000
0(
#1468000
b11 F
b10110101 C
0'
b1 L
1(
#1472000
0(
#1476000
b10110110 C
1'
b1 &
b1 -
1(
#1480000
0(
#1484000
b100 F
b10110111 C
0'
b0 L
1(
#1488000
0(
#1492000
b10111000 C
1'
b0 &
b0 -
1(
#1496000
0(
