sim/pkt_header_parser.v
// ============================================================
// HASS - Packet Header Parser
// Strips Ethernet, IP, TCP/UDP headers from raw byte stream
// Presents parsed fields as registered outputs to engines
// Target: Artix-7 XC7A100T @ 125 MHz
// ============================================================

module pkt_header_parser (
    input  wire        clk,
    input  wire        rst_n,

    // Raw byte stream from TEMAC
    input  wire [7:0]  byte_in,
    input  wire        byte_valid,
    input  wire        frame_start,  // pulse: start of new Ethernet frame
    input  wire        frame_end,    // pulse: end of frame

    // Parsed fields — registered, stable for duration of frame
    output reg [31:0]  src_ip,
    output reg [31:0]  dst_ip,
    output reg [15:0]  src_port,
    output reg [15:0]  dst_port,
    output reg [7:0]   protocol,     // 0x06=TCP, 0x11=UDP, 0x01=ICMP

    // TCP flag outputs (valid only when protocol == 0x06)
    output reg         is_syn,
    output reg         is_syn_ack,
    output reg         is_ack,
    output reg         is_fin,
    output reg         is_rst,

    // ARP outputs
    output reg         is_arp_reply, // ARP opcode == 2

    // Payload stream — byte stream forwarded AFTER all headers stripped
    // Engines connect here instead of to raw TEMAC output
    output reg [7:0]   payload_byte,
    output reg         payload_valid,
    output reg         payload_start, // pulses on first payload byte
    output reg         payload_end,   // mirrors frame_end

    // Header parse complete — safe to read all output fields
    output reg         hdr_valid
);

    // ----------------------------------------------------------
    // Ethernet header layout (14 bytes, no VLAN)
    // Byte 0-5  : Destination MAC
    // Byte 6-11 : Source MAC
    // Byte 12-13: EtherType
    //   0x0800 = IPv4
    //   0x0806 = ARP
    // ----------------------------------------------------------

    // ----------------------------------------------------------
    // IPv4 header layout (20 bytes minimum, no options handled)
    // Byte 0    : Version (4) + IHL (header length in 32-bit words)
    // Byte 1    : DSCP + ECN
    // Byte 2-3  : Total length
    // Byte 4-5  : Identification
    // Byte 6-7  : Flags + Fragment offset
    // Byte 8    : TTL
    // Byte 9    : Protocol
    // Byte 10-11: Header checksum
    // Byte 12-15: Source IP
    // Byte 16-19: Destination IP
    // ----------------------------------------------------------

    // ----------------------------------------------------------
    // TCP header layout (20 bytes minimum)
    // Byte 0-1  : Source port
    // Byte 2-3  : Destination port
    // Byte 4-7  : Sequence number
    // Byte 8-11 : Acknowledgment number
    // Byte 12   : Data offset (header length in 32-bit words) + reserved
    // Byte 13   : Flags (URG ACK PSH RST SYN FIN)
    // Byte 14-15: Window size
    // Byte 16-17: Checksum
    // Byte 18-19: Urgent pointer
    // ----------------------------------------------------------

    // ----------------------------------------------------------
    // UDP header layout (8 bytes)
    // Byte 0-1  : Source port
    // Byte 2-3  : Destination port
    // Byte 4-5  : Length
    // Byte 6-7  : Checksum
    // ----------------------------------------------------------

    // ----------------------------------------------------------
    // ARP header layout (28 bytes for IPv4)
    // Byte 0-1  : Hardware type
    // Byte 2-3  : Protocol type
    // Byte 4    : Hardware addr length
    // Byte 5    : Protocol addr length
    // Byte 6-7  : Opcode (1=request, 2=reply)
    // Byte 8-13 : Sender MAC
    // Byte 14-17: Sender IP
    // Byte 18-23: Target MAC
    // Byte 24-27: Target IP
    // ----------------------------------------------------------

    // ----------------------------------------------------------
    // Parser FSM states
    // ----------------------------------------------------------
    localparam S_IDLE        = 4'd0;
    localparam S_ETH_HDR     = 4'd1;   // consuming 14-byte Ethernet header
    localparam S_IP_HDR      = 4'd2;   // consuming 20-byte IPv4 header
    localparam S_TCP_HDR     = 4'd3;   // consuming 20-byte TCP header
    localparam S_UDP_HDR     = 4'd4;   // consuming 8-byte UDP header
    localparam S_ARP_HDR     = 4'd5;   // consuming 28-byte ARP payload
    localparam S_PAYLOAD     = 4'd6;   // forwarding payload bytes to engines
    localparam S_SKIP        = 4'd7;   // unknown EtherType — discard frame

    reg [3:0]  state;
    reg [7:0]  byte_count;   // position within current header section

    // Latched EtherType and IP fields needed across states
    reg [15:0] ethertype;
    reg [7:0]  ihl_bytes;    // IP header length in bytes (IHL field * 4)
    reg [7:0]  ip_hdr_remaining; // counts down through variable IP header
    reg [7:0]  tcp_data_offset_bytes; // TCP header length in bytes
    reg [7:0]  tcp_hdr_remaining;

    // ----------------------------------------------------------
    // Main parser FSM
    // ----------------------------------------------------------
    always @(posedge clk or negedge rst_n) begin
        if (!rst_n) begin
            state                 <= S_IDLE;
            byte_count            <= 0;
            ethertype             <= 0;
            ihl_bytes             <= 0;
            ip_hdr_remaining      <= 0;
            tcp_data_offset_bytes <= 0;
            tcp_hdr_remaining     <= 0;
            src_ip                <= 0;
            dst_ip                <= 0;
            src_port              <= 0;
            dst_port              <= 0;
            protocol              <= 0;
            is_syn                <= 0;
            is_syn_ack            <= 0;
            is_ack                <= 0;
            is_fin                <= 0;
            is_rst                <= 0;
            is_arp_reply          <= 0;
            payload_byte          <= 0;
            payload_valid         <= 0;
            payload_start         <= 0;
            payload_end           <= 0;
            hdr_valid             <= 0;
        end else begin

            // Default: deassert pulse outputs each cycle
            payload_valid <= 0;
            payload_start <= 0;
            payload_end   <= 0;
            hdr_valid     <= 0;

            if (frame_start) begin
                state      <= S_ETH_HDR;
                byte_count <= 0;
                // Clear all parsed fields at start of new frame
                src_ip       <= 0;
                dst_ip       <= 0;
                src_port     <= 0;
                dst_port     <= 0;
                protocol     <= 0;
                is_syn       <= 0;
                is_syn_ack   <= 0;
                is_ack       <= 0;
                is_fin       <= 0;
                is_rst       <= 0;
                is_arp_reply <= 0;
            end else if (frame_end) begin
                payload_end <= 1;
                state       <= S_IDLE;
            end else if (byte_valid) begin
                case (state)

                    // ------------------------------------------
                    // Ethernet header: 14 bytes
                    // Bytes 0-5:  dst MAC (ignored)
                    // Bytes 6-11: src MAC (ignored)
                    // Bytes 12-13: EtherType
                    // ------------------------------------------
                    S_ETH_HDR: begin
                        case (byte_count)
                            8'd12: ethertype[15:8] <= byte_in;
                            8'd13: begin
                                ethertype[7:0] <= byte_in;
                                byte_count     <= 0;
                                case ({ethertype[15:8], byte_in})
                                    16'h0800: state <= S_IP_HDR;  // IPv4
                                    16'h0806: state <= S_ARP_HDR; // ARP
                                    default:  state <= S_SKIP;    // unsupported
                                endcase
                            end
                            default: byte_count <= byte_count + 1;
                        endcase
                        if (byte_count != 8'd13)
                            byte_count <= byte_count + 1;
                    end

                    // ------------------------------------------
                    // IPv4 header: minimum 20 bytes
                    // IHL field tells us actual length
                    // ------------------------------------------
                    S_IP_HDR: begin
                        case (byte_count)
                            // Byte 0: Version + IHL
                            8'd0: begin
                                // IHL is bottom 4 bits, units of 32-bit words
                                // Multiply by 4 to get byte count
                                ihl_bytes        <= {byte_in[3:0], 2'b00};
                                ip_hdr_remaining <= {byte_in[3:0], 2'b00} - 1;
                            end
                            // Byte 9: Protocol
                            8'd9: protocol <= byte_in;
                            // Bytes 12-15: Source IP
                            8'd12: src_ip[31:24] <= byte_in;
                            8'd13: src_ip[23:16] <= byte_in;
                            8'd14: src_ip[15:8]  <= byte_in;
                            8'd15: src_ip[7:0]   <= byte_in;
                            // Bytes 16-19: Destination IP
                            8'd16: dst_ip[31:24] <= byte_in;
                            8'd17: dst_ip[23:16] <= byte_in;
                            8'd18: dst_ip[15:8]  <= byte_in;
                            8'd19: begin
                                dst_ip[7:0] <= byte_in;
                                // If IHL > 5 words (20 bytes), skip options
                                // ip_hdr_remaining was set at byte 0
                                // After byte 19 we've consumed 20 bytes
                                // If ihl_bytes > 20, remaining options follow
                            end
                        endcase

                        // Transition: when we've consumed ihl_bytes bytes
                        if (byte_count == ihl_bytes - 1) begin
                            byte_count <= 0;
                            case (protocol)
                                8'h06: state <= S_TCP_HDR;
                                8'h11: state <= S_UDP_HDR;
                                default: state <= S_SKIP; // ICMP etc — no ports
                            endcase
                        end else begin
                            byte_count <= byte_count + 1;
                        end
                    end

                    // ------------------------------------------
                    // TCP header: minimum 20 bytes
                    // Data offset field gives actual length
                    // ------------------------------------------
                    S_TCP_HDR: begin
                        case (byte_count)
                            // Bytes 0-1: Source port
                            8'd0: src_port[15:8] <= byte_in;
                            8'd1: src_port[7:0]  <= byte_in;
                            // Bytes 2-3: Destination port
                            8'd2: dst_port[15:8] <= byte_in;
                            8'd3: dst_port[7:0]  <= byte_in;
                            // Byte 12: Data offset (high 4 bits) + reserved
                            8'd12: begin
                                // Data offset in 32-bit words, multiply by 4
                                tcp_data_offset_bytes <= {byte_in[7:4], 2'b00};
                                tcp_hdr_remaining     <= {byte_in[7:4], 2'b00} - 1;
                            end
                            // Byte 13: Flags
                            8'd13: begin
                                is_fin     <= byte_in[0];
                                is_syn     <= byte_in[1];
                                is_rst     <= byte_in[2];
                                is_ack     <= byte_in[4];
                                is_syn_ack <= byte_in[1] & byte_in[4]; // SYN+ACK
                            end
                        endcase

                        if (byte_count == tcp_data_offset_bytes - 1) begin
                            byte_count    <= 0;
                            hdr_valid     <= 1;  // all fields now stable
                            payload_start <= 1;
                            state         <= S_PAYLOAD;
                        end else begin
                            byte_count <= byte_count + 1;
                        end
                    end

                    // ------------------------------------------
                    // UDP header: fixed 8 bytes
                    // ------------------------------------------
                    S_UDP_HDR: begin
                        case (byte_count)
                            8'd0: src_port[15:8] <= byte_in;
                            8'd1: src_port[7:0]  <= byte_in;
                            8'd2: dst_port[15:8] <= byte_in;
                            8'd3: dst_port[7:0]  <= byte_in;
                            // Bytes 4-5: length, 6-7: checksum — ignored
                            8'd7: begin
                                hdr_valid     <= 1;
                                payload_start <= 1;
                                byte_count    <= 0;
                                state         <= S_PAYLOAD;
                            end
                        endcase
                        if (byte_count != 8'd7)
                            byte_count <= byte_count + 1;
                    end

                    // ------------------------------------------
                    // ARP header: 28 bytes for IPv4/Ethernet
                    // We only care about opcode (bytes 6-7)
                    // ------------------------------------------
                    S_ARP_HDR: begin
                        case (byte_count)
                            8'd6: ; // opcode high byte — always 0x00
                            8'd7: begin
                                is_arp_reply <= (byte_in == 8'd2);
                                hdr_valid    <= 1;
                            end
                        endcase
                        if (byte_count == 8'd27) begin
                            // ARP has no payload — wait for frame_end
                            state      <= S_SKIP;
                            byte_count <= 0;
                        end else begin
                            byte_count <= byte_count + 1;
                        end
                    end

                    // ------------------------------------------
                    // Payload forwarding: pass bytes to engines
                    // ------------------------------------------
                    S_PAYLOAD: begin
                        payload_byte  <= byte_in;
                        payload_valid <= 1;
                    end

                    // Unknown or unsupported frame type — drain silently
                    S_SKIP: begin end

                    default: state <= S_IDLE;
                endcase
            end
        end
    end

endmodule

sim/tb_pkt_parser.v
`timescale 1ns/1ps

module tb_pkt_parser;

    reg        clk         = 0;
    reg        rst_n       = 0;
    reg [7:0]  byte_in     = 0;
    reg        byte_valid  = 0;
    reg        frame_start = 0;
    reg        frame_end   = 0;

    wire [31:0] src_ip;
    wire [31:0] dst_ip;
    wire [15:0] src_port;
    wire [15:0] dst_port;
    wire [7:0]  protocol;
    wire        is_syn, is_syn_ack, is_ack, is_fin, is_rst;
    wire        is_arp_reply;
    wire [7:0]  payload_byte;
    wire        payload_valid;
    wire        payload_start;
    wire        payload_end;
    wire        hdr_valid;

    pkt_header_parser u_dut (
        .clk          (clk),
        .rst_n        (rst_n),
        .byte_in      (byte_in),
        .byte_valid   (byte_valid),
        .frame_start  (frame_start),
        .frame_end    (frame_end),
        .src_ip       (src_ip),
        .dst_ip       (dst_ip),
        .src_port     (src_port),
        .dst_port     (dst_port),
        .protocol     (protocol),
        .is_syn       (is_syn),
        .is_syn_ack   (is_syn_ack),
        .is_ack       (is_ack),
        .is_fin       (is_fin),
        .is_rst       (is_rst),
        .is_arp_reply (is_arp_reply),
        .payload_byte (payload_byte),
        .payload_valid(payload_valid),
        .payload_start(payload_start),
        .payload_end  (payload_end),
        .hdr_valid    (hdr_valid)
    );

    always #4 clk = ~clk;  // 125 MHz

    initial begin
        $dumpfile("tb_pkt_parser.vcd");
        $dumpvars(0, tb_pkt_parser);
    end

    // Task: send one byte into the parser
    task send_byte;
        input [7:0] b;
        begin
            @(posedge clk);
            byte_in    <= b;
            byte_valid <= 1;
            @(posedge clk);
            byte_valid <= 0;
        end
    endtask

    // Task: send a full frame byte array
    // We'll call this manually below for clarity
    task start_frame;
        begin
            @(posedge clk);
            frame_start <= 1;
            @(posedge clk);
            frame_start <= 0;
        end
    endtask

    task end_frame;
        begin
            @(posedge clk);
            frame_end <= 1;
            @(posedge clk);
            frame_end <= 0;
        end
    endtask

    initial begin
        // Reset
        rst_n = 0;
        repeat(4) @(posedge clk);
        rst_n = 1;
        repeat(2) @(posedge clk);

        // -------------------------------------------------------
        // TEST 1: IPv4/UDP frame
        // src_ip  = 192.168.1.10
        // dst_ip  = 8.8.8.8
        // src_port = 5000
        // dst_port = 53  (DNS)
        // -------------------------------------------------------
        $display("--- TEST 1: IPv4/UDP ---");
        start_frame;

        // Ethernet header (14 bytes)
        // Dst MAC: FF:FF:FF:FF:FF:FF
        send_byte(8'hFF); send_byte(8'hFF); send_byte(8'hFF);
        send_byte(8'hFF); send_byte(8'hFF); send_byte(8'hFF);
        // Src MAC: AA:BB:CC:DD:EE:FF
        send_byte(8'hAA); send_byte(8'hBB); send_byte(8'hCC);
        send_byte(8'hDD); send_byte(8'hEE); send_byte(8'hFF);
        // EtherType: 0x0800 (IPv4)
        send_byte(8'h08); send_byte(8'h00);

        // IPv4 header (20 bytes, IHL=5)
        send_byte(8'h45); // Version=4, IHL=5
        send_byte(8'h00); // DSCP/ECN
        send_byte(8'h00); send_byte(8'h1C); // Total length
        send_byte(8'h00); send_byte(8'h01); // ID
        send_byte(8'h00); send_byte(8'h00); // Flags/Fragment
        send_byte(8'h40); // TTL=64
        send_byte(8'h11); // Protocol=UDP (0x11)
        send_byte(8'h00); send_byte(8'h00); // Header checksum
        // src_ip = 192.168.1.10
        send_byte(8'hC0); send_byte(8'hA8); send_byte(8'h01); send_byte(8'h0A);
        // dst_ip = 8.8.8.8
        send_byte(8'h08); send_byte(8'h08); send_byte(8'h08); send_byte(8'h08);

        // UDP header (8 bytes)
        // src_port = 5000 = 0x1388
        send_byte(8'h13); send_byte(8'h88);
        // dst_port = 53 = 0x0035
        send_byte(8'h00); send_byte(8'h35);
        send_byte(8'h00); send_byte(8'h08); // length
        send_byte(8'h00); send_byte(8'h00); // checksum

        // Payload (4 bytes — dummy DNS data)
        send_byte(8'hAB); send_byte(8'hCD);
        send_byte(8'hEF); send_byte(8'h01);

        end_frame;
        repeat(4) @(posedge clk);

        // Check results
        if (src_ip == 32'hC0A8010A)
            $display("PASS: src_ip = 192.168.1.10");
        else
            $display("FAIL: src_ip = %h (expected C0A8010A)", src_ip);

        if (dst_ip == 32'h08080808)
            $display("PASS: dst_ip = 8.8.8.8");
        else
            $display("FAIL: dst_ip = %h (expected 08080808)", dst_ip);

        if (protocol == 8'h11)
            $display("PASS: protocol = UDP");
        else
            $display("FAIL: protocol = %h (expected 11)", protocol);

        if (src_port == 16'h1388)
            $display("PASS: src_port = 5000");
        else
            $display("FAIL: src_port = %h (expected 1388)", src_port);

        if (dst_port == 16'h0035)
            $display("PASS: dst_port = 53");
        else
            $display("FAIL: dst_port = %h (expected 0035)", dst_port);

        repeat(4) @(posedge clk);

        // -------------------------------------------------------
        // TEST 2: IPv4/TCP SYN frame
        // src_ip  = 10.0.0.1
        // dst_ip  = 10.0.0.2
        // src_port = 12345
        // dst_port = 80 (HTTP)
        // flags: SYN only
        // -------------------------------------------------------
        $display("--- TEST 2: IPv4/TCP SYN ---");
        start_frame;

        // Ethernet header
        send_byte(8'hFF); send_byte(8'hFF); send_byte(8'hFF);
        send_byte(8'hFF); send_byte(8'hFF); send_byte(8'hFF);
        send_byte(8'h11); send_byte(8'h22); send_byte(8'h33);
        send_byte(8'h44); send_byte(8'h55); send_byte(8'h66);
        send_byte(8'h08); send_byte(8'h00);

        // IPv4 header
        send_byte(8'h45); send_byte(8'h00);
        send_byte(8'h00); send_byte(8'h28);
        send_byte(8'h00); send_byte(8'h02);
        send_byte(8'h00); send_byte(8'h00);
        send_byte(8'h40);
        send_byte(8'h06); // Protocol=TCP
        send_byte(8'h00); send_byte(8'h00);
        // src_ip = 10.0.0.1
        send_byte(8'h0A); send_byte(8'h00); send_byte(8'h00); send_byte(8'h01);
        // dst_ip = 10.0.0.2
        send_byte(8'h0A); send_byte(8'h00); send_byte(8'h00); send_byte(8'h02);

        // TCP header (20 bytes, data offset=5)
        // src_port = 12345 = 0x3039
        send_byte(8'h30); send_byte(8'h39);
        // dst_port = 80 = 0x0050
        send_byte(8'h00); send_byte(8'h50);
        // Seq number
        send_byte(8'h00); send_byte(8'h00); send_byte(8'h00); send_byte(8'h01);
        // Ack number
        send_byte(8'h00); send_byte(8'h00); send_byte(8'h00); send_byte(8'h00);
        // Data offset=5 (0x50), reserved=0
        send_byte(8'h50);
        // Flags: SYN only = 0x02
        send_byte(8'h02);
        // Window
        send_byte(8'hFF); send_byte(8'hFF);
        // Checksum, urgent
        send_byte(8'h00); send_byte(8'h00);
        send_byte(8'h00); send_byte(8'h00);

        end_frame;
        repeat(4) @(posedge clk);

        if (protocol == 8'h06)
            $display("PASS: protocol = TCP");
        else
            $display("FAIL: protocol = %h (expected 06)", protocol);

        if (is_syn && !is_ack)
            $display("PASS: SYN flag set, ACK clear");
        else
            $display("FAIL: SYN=%b ACK=%b (expected SYN=1 ACK=0)", is_syn, is_ack);

        if (dst_port == 16'h0050)
            $display("PASS: dst_port = 80");
        else
            $display("FAIL: dst_port = %h (expected 0050)", dst_port);

        repeat(4) @(posedge clk);
        $display("Simulation complete.");
        $finish;
    end

endmodule

sim/tb_pkt_parser.vcd
$date
	Thu Jun 18 20:48:08 2026
$end
$version
	Icarus Verilog
$end
$timescale
	1ps
$end
$scope module tb_pkt_parser $end
$var wire 16 ! src_port [15:0] $end
$var wire 32 " src_ip [31:0] $end
$var wire 8 # protocol [7:0] $end
$var wire 1 $ payload_valid $end
$var wire 1 % payload_start $end
$var wire 1 & payload_end $end
$var wire 8 ' payload_byte [7:0] $end
$var wire 1 ( is_syn_ack $end
$var wire 1 ) is_syn $end
$var wire 1 * is_rst $end
$var wire 1 + is_fin $end
$var wire 1 , is_arp_reply $end
$var wire 1 - is_ack $end
$var wire 1 . hdr_valid $end
$var wire 16 / dst_port [15:0] $end
$var wire 32 0 dst_ip [31:0] $end
$var reg 8 1 byte_in [7:0] $end
$var reg 1 2 byte_valid $end
$var reg 1 3 clk $end
$var reg 1 4 frame_end $end
$var reg 1 5 frame_start $end
$var reg 1 6 rst_n $end
$scope module u_dut $end
$var wire 8 7 byte_in [7:0] $end
$var wire 1 2 byte_valid $end
$var wire 1 3 clk $end
$var wire 1 4 frame_end $end
$var wire 1 5 frame_start $end
$var wire 1 6 rst_n $end
$var parameter 4 8 S_ARP_HDR $end
$var parameter 4 9 S_ETH_HDR $end
$var parameter 4 : S_IDLE $end
$var parameter 4 ; S_IP_HDR $end
$var parameter 4 < S_PAYLOAD $end
$var parameter 4 = S_SKIP $end
$var parameter 4 > S_TCP_HDR $end
$var parameter 4 ? S_UDP_HDR $end
$var reg 8 @ byte_count [7:0] $end
$var reg 32 A dst_ip [31:0] $end
$var reg 16 B dst_port [15:0] $end
$var reg 16 C ethertype [15:0] $end
$var reg 1 . hdr_valid $end
$var reg 8 D ihl_bytes [7:0] $end
$var reg 8 E ip_hdr_remaining [7:0] $end
$var reg 1 - is_ack $end
$var reg 1 , is_arp_reply $end
$var reg 1 + is_fin $end
$var reg 1 * is_rst $end
$var reg 1 ) is_syn $end
$var reg 1 ( is_syn_ack $end
$var reg 8 F payload_byte [7:0] $end
$var reg 1 & payload_end $end
$var reg 1 % payload_start $end
$var reg 1 $ payload_valid $end
$var reg 8 G protocol [7:0] $end
$var reg 32 H src_ip [31:0] $end
$var reg 16 I src_port [15:0] $end
$var reg 4 J state [3:0] $end
$var reg 8 K tcp_data_offset_bytes [7:0] $end
$var reg 8 L tcp_hdr_remaining [7:0] $end
$upscope $end
$scope task end_frame $end
$upscope $end
$scope task send_byte $end
$var reg 8 M b [7:0] $end
$upscope $end
$scope task start_frame $end
$upscope $end
$upscope $end
$enddefinitions $end
$comment Show the parameter values. $end
$dumpall
b100 ?
b11 >
b111 =
b110 <
b10 ;
b0 :
b1 9
b101 8
$end
#0
$dumpvars
bx M
b0 L
b0 K
b0 J
b0 I
b0 H
b0 G
b0 F
b0 E
b0 D
b0 C
b0 B
b0 A
b0 @
b0 7
06
05
04
03
02
b0 1
b0 0
b0 /
0.
0-
0,
0+
0*
0)
0(
b0 '
0&
0%
0$
b0 #
b0 "
b0 !
$end
#4000
13
#8000
03
#12000
13
#16000
03
#20000
13
#24000
03
#28000
16
13
#32000
03
#36000
13
#40000
03
#44000
13
#48000
03
#52000
15
13
#56000
03
#60000
b1 J
05
b11111111 M
13
#64000
03
#68000
12
b11111111 1
b11111111 7
13
#72000
03
#76000
b1 @
02
13
#80000
03
#84000
12
13
#88000
03
#92000
b10 @
02
13
#96000
03
#100000
12
13
#104000
03
#108000
b11 @
02
13
#112000
03
#116000
12
13
#120000
03
#124000
b100 @
02
13
#128000
03
#132000
12
13
#136000
03
#140000
b101 @
02
13
#144000
03
#148000
12
13
#152000
03
#156000
b110 @
02
b10101010 M
13
#160000
03
#164000
12
b10101010 1
b10101010 7
13
#168000
03
#172000
b111 @
02
b10111011 M
13
#176000
03
#180000
12
b10111011 1
b10111011 7
13
#184000
03
#188000
b1000 @
02
b11001100 M
13
#192000
03
#196000
12
b11001100 1
b11001100 7
13
#200000
03
#204000
b1001 @
02
b11011101 M
13
#208000
03
#212000
12
b11011101 1
b11011101 7
13
#216000
03
#220000
b1010 @
02
b11101110 M
13
#224000
03
#228000
12
b11101110 1
b11101110 7
13
#232000
03
#236000
b1011 @
02
b11111111 M
13
#240000
03
#244000
12
b11111111 1
b11111111 7
13
#248000
03
#252000
b1100 @
02
b1000 M
13
#256000
03
#260000
12
b1000 1
b1000 7
13
#264000
03
#268000
b1101 @
b100000000000 C
02
b0 M
13
#272000
03
#276000
12
b0 1
b0 7
13
#280000
03
#284000
b10 J
b0 @
02
b1000101 M
13
#288000
03
#292000
12
b1000101 1
b1000101 7
13
#296000
03
#300000
b1 @
b10011 E
b10100 D
02
b0 M
13
#304000
03
#308000
12
b0 1
b0 7
13
#312000
03
#316000
b10 @
02
13
#320000
03
#324000
12
13
#328000
03
#332000
b11 @
02
b11100 M
13
#336000
03
#340000
12
b11100 1
b11100 7
13
#344000
03
#348000
b100 @
02
b0 M
13
#352000
03
#356000
12
b0 1
b0 7
13
#360000
03
#364000
b101 @
02
b1 M
13
#368000
03
#372000
12
b1 1
b1 7
13
#376000
03
#380000
b110 @
02
b0 M
13
#384000
03
#388000
12
b0 1
b0 7
13
#392000
03
#396000
b111 @
02
13
#400000
03
#404000
12
13
#408000
03
#412000
b1000 @
02
b1000000 M
13
#416000
03
#420000
12
b1000000 1
b1000000 7
13
#424000
03
#428000
b1001 @
02
b10001 M
13
#432000
03
#436000
12
b10001 1
b10001 7
13
#440000
03
#444000
b1010 @
b10001 #
b10001 G
02
b0 M
13
#448000
03
#452000
12
b0 1
b0 7
13
#456000
03
#460000
b1011 @
02
13
#464000
03
#468000
12
13
#472000
03
#476000
b1100 @
02
b11000000 M
13
#480000
03
#484000
12
b11000000 1
b11000000 7
13
#488000
03
#492000
b1101 @
b11000000000000000000000000000000 "
b11000000000000000000000000000000 H
02
b10101000 M
13
#496000
03
#500000
12
b10101000 1
b10101000 7
13
#504000
03
#508000
b1110 @
b11000000101010000000000000000000 "
b11000000101010000000000000000000 H
02
b1 M
13
#512000
03
#516000
12
b1 1
b1 7
13
#520000
03
#524000
b1111 @
b11000000101010000000000100000000 "
b11000000101010000000000100000000 H
02
b1010 M
13
#528000
03
#532000
12
b1010 1
b1010 7
13
#536000
03
#540000
b10000 @
b11000000101010000000000100001010 "
b11000000101010000000000100001010 H
02
b1000 M
13
#544000
03
#548000
12
b1000 1
b1000 7
13
#552000
03
#556000
b10001 @
b1000000000000000000000000000 0
b1000000000000000000000000000 A
02
13
#560000
03
#564000
12
13
#568000
03
#572000
b10010 @
b1000000010000000000000000000 0
b1000000010000000000000000000 A
02
13
#576000
03
#580000
12
13
#584000
03
#588000
b10011 @
b1000000010000000100000000000 0
b1000000010000000100000000000 A
02
13
#592000
03
#596000
12
13
#600000
03
#604000
b100 J
b0 @
b1000000010000000100000001000 0
b1000000010000000100000001000 A
02
b10011 M
13
#608000
03
#612000
12
b10011 1
b10011 7
13
#616000
03
#620000
b1 @
b1001100000000 !
b1001100000000 I
02
b10001000 M
13
#624000
03
#628000
12
b10001000 1
b10001000 7
13
#632000
03
#636000
b10 @
b1001110001000 !
b1001110001000 I
02
b0 M
13
#640000
03
#644000
12
b0 1
b0 7
13
#648000
03
#652000
b11 @
02
b110101 M
13
#656000
03
#660000
12
b110101 1
b110101 7
13
#664000
03
#668000
b100 @
b110101 /
b110101 B
02
b0 M
13
#672000
03
#676000
12
b0 1
b0 7
13
#680000
03
#684000
b101 @
02
b1000 M
13
#688000
03
#692000
12
b1000 1
b1000 7
13
#696000
03
#700000
b110 @
02
b0 M
13
#704000
03
#708000
12
b0 1
b0 7
13
#712000
03
#716000
b111 @
02
13
#720000
03
#724000
12
13
#728000
03
#732000
b110 J
b0 @
1%
1.
02
b10101011 M
13
#736000
03
#740000
0.
0%
12
b10101011 1
b10101011 7
13
#744000
03
#748000
1$
b10101011 '
b10101011 F
02
b11001101 M
13
#752000
03
#756000
0$
12
b11001101 1
b11001101 7
13
#760000
03
#764000
1$
b11001101 '
b11001101 F
02
b11101111 M
13
#768000
03
#772000
0$
12
b11101111 1
b11101111 7
13
#776000
03
#780000
1$
b11101111 '
b11101111 F
02
b1 M
13
#784000
03
#788000
0$
12
b1 1
b1 7
13
#792000
03
#796000
1$
b1 '
b1 F
02
13
#800000
03
#804000
0$
14
13
#808000
03
#812000
b0 J
1&
04
13
#816000
03
#820000
0&
13
#824000
03
#828000
13
#832000
03
#836000
13
#840000
03
#844000
13
#848000
03
#852000
13
#856000
03
#860000
13
#864000
03
#868000
13
#872000
03
#876000
13
#880000
03
#884000
15
13
#888000
03
#892000
b0 #
b0 G
b0 /
b0 B
b0 !
b0 I
b0 0
b0 A
b0 "
b0 H
b1 J
05
b11111111 M
13
#896000
03
#900000
12
b11111111 1
b11111111 7
13
#904000
03
#908000
b1 @
02
13
#912000
03
#916000
12
13
#920000
03
#924000
b10 @
02
13
#928000
03
#932000
12
13
#936000
03
#940000
b11 @
02
13
#944000
03
#948000
12
13
#952000
03
#956000
b100 @
02
13
#960000
03
#964000
12
13
#968000
03
#972000
b101 @
02
13
#976000
03
#980000
12
13
#984000
03
#988000
b110 @
02
b10001 M
13
#992000
03
#996000
12
b10001 1
b10001 7
13
#1000000
03
#1004000
b111 @
02
b100010 M
13
#1008000
03
#1012000
12
b100010 1
b100010 7
13
#1016000
03
#1020000
b1000 @
02
b110011 M
13
#1024000
03
#1028000
12
b110011 1
b110011 7
13
#1032000
03
#1036000
b1001 @
02
b1000100 M
13
#1040000
03
#1044000
12
b1000100 1
b1000100 7
13
#1048000
03
#1052000
b1010 @
02
b1010101 M
13
#1056000
03
#1060000
12
b1010101 1
b1010101 7
13
#1064000
03
#1068000
b1011 @
02
b1100110 M
13
#1072000
03
#1076000
12
b1100110 1
b1100110 7
13
#1080000
03
#1084000
b1100 @
02
b1000 M
13
#1088000
03
#1092000
12
b1000 1
b1000 7
13
#1096000
03
#1100000
b1101 @
02
b0 M
13
#1104000
03
#1108000
12
b0 1
b0 7
13
#1112000
03
#1116000
b10 J
b0 @
02
b1000101 M
13
#1120000
03
#1124000
12
b1000101 1
b1000101 7
13
#1128000
03
#1132000
b1 @
02
b0 M
13
#1136000
03
#1140000
12
b0 1
b0 7
13
#1144000
03
#1148000
b10 @
02
13
#1152000
03
#1156000
12
13
#1160000
03
#1164000
b11 @
02
b101000 M
13
#1168000
03
#1172000
12
b101000 1
b101000 7
13
#1176000
03
#1180000
b100 @
02
b0 M
13
#1184000
03
#1188000
12
b0 1
b0 7
13
#1192000
03
#1196000
b101 @
02
b10 M
13
#1200000
03
#1204000
12
b10 1
b10 7
13
#1208000
03
#1212000
b110 @
02
b0 M
13
#1216000
03
#1220000
12
b0 1
b0 7
13
#1224000
03
#1228000
b111 @
02
13
#1232000
03
#1236000
12
13
#1240000
03
#1244000
b1000 @
02
b1000000 M
13
#1248000
03
#1252000
12
b1000000 1
b1000000 7
13
#1256000
03
#1260000
b1001 @
02
b110 M
13
#1264000
03
#1268000
12
b110 1
b110 7
13
#1272000
03
#1276000
b1010 @
b110 #
b110 G
02
b0 M
13
#1280000
03
#1284000
12
b0 1
b0 7
13
#1288000
03
#1292000
b1011 @
02
13
#1296000
03
#1300000
12
13
#1304000
03
#1308000
b1100 @
02
b1010 M
13
#1312000
03
#1316000
12
b1010 1
b1010 7
13
#1320000
03
#1324000
b1101 @
b1010000000000000000000000000 "
b1010000000000000000000000000 H
02
b0 M
13
#1328000
03
#1332000
12
b0 1
b0 7
13
#1336000
03
#1340000
b1110 @
02
13
#1344000
03
#1348000
12
13
#1352000
03
#1356000
b1111 @
02
b1 M
13
#1360000
03
#1364000
12
b1 1
b1 7
13
#1368000
03
#1372000
b10000 @
b1010000000000000000000000001 "
b1010000000000000000000000001 H
02
b1010 M
13
#1376000
03
#1380000
12
b1010 1
b1010 7
13
#1384000
03
#1388000
b10001 @
b1010000000000000000000000000 0
b1010000000000000000000000000 A
02
b0 M
13
#1392000
03
#1396000
12
b0 1
b0 7
13
#1400000
03
#1404000
b10010 @
02
13
#1408000
03
#1412000
12
13
#1416000
03
#1420000
b10011 @
02
b10 M
13
#1424000
03
#1428000
12
b10 1
b10 7
13
#1432000
03
#1436000
b11 J
b0 @
b1010000000000000000000000010 0
b1010000000000000000000000010 A
02
b110000 M
13
#1440000
03
#1444000
12
b110000 1
b110000 7
13
