sim/rate_monitor.v
// ============================================================
// HASS - Rate & Flow Monitor
// Maintains per-flow state for 64 concurrent flows
// Flags: ARP spoofing, SYN flood, C2 beaconing
// Target: Artix-7 XC7A100T @ 125 MHz
// ============================================================

module rate_monitor (
    input  wire        clk,
    input  wire        rst_n,

    // Parsed header fields from hass_top packet parser
    input  wire [31:0] src_ip,
    input  wire [31:0] dst_ip,
    input  wire [15:0] src_port,
    input  wire [15:0] dst_port,
    input  wire [7:0]  protocol,    // 0x06=TCP, 0x11=UDP, 0x00=ARP
    input  wire        pkt_valid,   // pulse: new packet header available
    input  wire        is_syn,      // TCP SYN flag set
    input  wire        is_syn_ack,  // TCP SYN-ACK flag set
    input  wire        is_arp_reply,// ARP opcode = 2

    // Alert outputs
    output reg         rate_alert,
    output reg [1:0]   alert_type   // 0=ARP spoof, 1=SYN flood, 2=C2 beacon
);

    // ----------------------------------------------------------
    // Flow table: 64 slots, indexed by hash of 4-tuple
    // Each slot stores:
    //   src_ip, dst_ip, src_port, dst_port (for collision check)
    //   pkt_count   — total packets this flow
    //   syn_count   — SYN packets seen
    //   synack_count— SYN-ACK packets seen
    //   byte_count  — total bytes (from hass_top, not shown here)
    //   age_timer   — counts down; slot freed when zero
    // ----------------------------------------------------------
    localparam FLOW_SLOTS = 64;
    localparam SLOT_BITS  = 6;   // log2(64)

    // Flow table registers
    reg [31:0] ft_src_ip    [0:FLOW_SLOTS-1];
    reg [31:0] ft_dst_ip    [0:FLOW_SLOTS-1];
    reg [15:0] ft_src_port  [0:FLOW_SLOTS-1];
    reg [15:0] ft_dst_port  [0:FLOW_SLOTS-1];
    reg [15:0] ft_pkt_count [0:FLOW_SLOTS-1];
    reg [7:0]  ft_syn_count [0:FLOW_SLOTS-1];
    reg [7:0]  ft_synack    [0:FLOW_SLOTS-1];
    reg [15:0] ft_age       [0:FLOW_SLOTS-1];
    reg        ft_valid     [0:FLOW_SLOTS-1]; // slot occupied

    // ARP reply rate counter (global, not per-flow)
    reg [7:0]  arp_reply_count;
    reg [19:0] arp_window_timer;    // ~8ms window @ 125 MHz

    // Thresholds
    localparam ARP_THRESH    = 8'd20;   // >20 ARP replies per 8ms = spoofing
    localparam SYN_THRESH    = 8'd30;   // >30 SYNs with <5 SYN-ACKs = flood
    localparam BEACON_THRESH = 16'd50;  // >50 pkts/window to same dst = beaconing
    localparam FLOW_AGE_MAX  = 16'hFFFF;

    // ----------------------------------------------------------
    // Hash function: XOR fold of 4-tuple to 6-bit slot index
    // Simple but sufficient for 64-slot table
    // ----------------------------------------------------------
    function [SLOT_BITS-1:0] flow_hash;
        input [31:0] sip;
        input [31:0] dip;
        input [15:0] sp;
        input [15:0] dp;
        reg [31:0] h;
        begin
            h = sip ^ dip ^ {sp, dp};
            flow_hash = h[5:0] ^ h[11:6] ^ h[17:12] ^ h[23:18] ^ {4'b0, h[25:24]};
        end
    endfunction

    // ----------------------------------------------------------
    // Slot lookup: find matching slot or first empty
    // Returns slot index and hit/miss flag
    // Done combinatorially — 64-entry CAM scan
    // ----------------------------------------------------------
    reg [SLOT_BITS-1:0] hash_idx;
    reg [SLOT_BITS-1:0] matched_slot;
    reg                 slot_hit;
    reg [SLOT_BITS-1:0] free_slot;
    reg                 free_found;

    integer s;
    always @(*) begin
        hash_idx     = flow_hash(src_ip, dst_ip, src_port, dst_port);
        matched_slot = 0;
        slot_hit     = 0;
        free_slot    = 0;
        free_found   = 0;

        for (s = 0; s < FLOW_SLOTS; s = s + 1) begin
            if (ft_valid[s] &&
                ft_src_ip[s]   == src_ip   &&
                ft_dst_ip[s]   == dst_ip   &&
                ft_src_port[s] == src_port &&
                ft_dst_port[s] == dst_port) begin
                matched_slot = s[SLOT_BITS-1:0];
                slot_hit     = 1;
            end
            if (!ft_valid[s] && !free_found) begin
                free_slot  = s[SLOT_BITS-1:0];
                free_found = 1;
            end
        end
    end

    // ----------------------------------------------------------
    // ARP reply rate monitor (global window)
    // ----------------------------------------------------------
    always @(posedge clk or negedge rst_n) begin
        if (!rst_n) begin
            arp_reply_count  <= 0;
            arp_window_timer <= 0;
        end else begin
            if (arp_window_timer == 20'hFFFFF) begin
                arp_window_timer <= 0;
                arp_reply_count  <= 0;
            end else begin
                arp_window_timer <= arp_window_timer + 1;
            end

            if (pkt_valid && is_arp_reply) begin
                arp_reply_count <= arp_reply_count + 1;
            end
        end
    end

    // ----------------------------------------------------------
    // Per-flow state update + alert FSM
    // ----------------------------------------------------------
    integer j;
    always @(posedge clk or negedge rst_n) begin
        if (!rst_n) begin
            rate_alert <= 0;
            alert_type <= 0;
            for (j = 0; j < FLOW_SLOTS; j = j + 1) begin
                ft_valid[j]     <= 0;
                ft_pkt_count[j] <= 0;
                ft_syn_count[j] <= 0;
                ft_synack[j]    <= 0;
                ft_age[j]       <= 0;
                ft_src_ip[j]    <= 0;
                ft_dst_ip[j]    <= 0;
                ft_src_port[j]  <= 0;
                ft_dst_port[j]  <= 0;
            end
        end else begin
            rate_alert <= 0;

            // Age all flows every cycle (decrement timer)
            for (j = 0; j < FLOW_SLOTS; j = j + 1) begin
                if (ft_valid[j]) begin
                    if (ft_age[j] == 0)
                        ft_valid[j] <= 0;  // expire old flow
                    else
                        ft_age[j] <= ft_age[j] - 1;
                end
            end

            // ARP spoof check — purely rate based, no flow needed
            if (arp_reply_count >= ARP_THRESH) begin
                rate_alert <= 1;
                alert_type <= 2'd0;
            end

            // Per-packet flow update
            if (pkt_valid && !is_arp_reply) begin
                if (slot_hit) begin
                    // Update existing flow
                    ft_pkt_count[matched_slot] <= ft_pkt_count[matched_slot] + 1;
                    ft_age[matched_slot]        <= FLOW_AGE_MAX;

                    if (is_syn)
                        ft_syn_count[matched_slot] <= ft_syn_count[matched_slot] + 1;
                    if (is_syn_ack)
                        ft_synack[matched_slot] <= ft_synack[matched_slot] + 1;

                    $display("    DEBUG: slot=%0d syn_count=%0d synack=%0d pkt_count=%0d",
                             matched_slot, ft_syn_count[matched_slot], ft_synack[matched_slot],
                             ft_pkt_count[matched_slot]);

                    // SYN flood: many SYNs, very few SYN-ACKs
                    if (ft_syn_count[matched_slot] >= SYN_THRESH &&
                        ft_synack[matched_slot] < 8'd5) begin
                        rate_alert <= 1;
                        alert_type <= 2'd1;
                    end

                    // C2 beaconing: abnormally high packet rate to same dst
                    if (ft_pkt_count[matched_slot] >= BEACON_THRESH) begin
                        rate_alert <= 1;
                        alert_type <= 2'd2;
                    end

                end else if (free_found) begin
                    // Insert new flow into free slot
                    ft_valid[free_slot]     <= 1;
                    ft_src_ip[free_slot]    <= src_ip;
                    ft_dst_ip[free_slot]    <= dst_ip;
                    ft_src_port[free_slot]  <= src_port;
                    ft_dst_port[free_slot]  <= dst_port;
                    ft_pkt_count[free_slot] <= 1;
                    ft_syn_count[free_slot] <= is_syn ? 1 : 0;
                    ft_synack[free_slot]    <= is_syn_ack ? 1 : 0;
                    ft_age[free_slot]       <= FLOW_AGE_MAX;
                end
                // If no free slot and no hit: table full, packet untracked
                // This is acceptable — degrades gracefully under flood conditions
            end
        end
    end

endmodule

sim/tb_rate_monitor.v
`timescale 1ns/1ps

module tb_rate_monitor;

    reg        clk         = 0;
    reg        rst_n       = 0;
    reg [31:0] src_ip      = 0;
    reg [31:0] dst_ip      = 0;
    reg [15:0] src_port    = 0;
    reg [15:0] dst_port    = 0;
    reg [7:0]  protocol    = 0;
    reg        pkt_valid   = 0;
    reg        is_syn      = 0;
    reg        is_syn_ack  = 0;
    reg        is_arp_reply= 0;

    wire        rate_alert;
    wire [1:0]  alert_type;

    rate_monitor u_dut (
        .clk          (clk),
        .rst_n        (rst_n),
        .src_ip       (src_ip),
        .dst_ip       (dst_ip),
        .src_port     (src_port),
        .dst_port     (dst_port),
        .protocol     (protocol),
        .pkt_valid    (pkt_valid),
        .is_syn       (is_syn),
        .is_syn_ack   (is_syn_ack),
        .is_arp_reply (is_arp_reply),
        .rate_alert   (rate_alert),
        .alert_type   (alert_type)
    );

    always #4 clk = ~clk;  // 125 MHz

    initial begin
        $dumpfile("tb_rate_monitor.vcd");
        $dumpvars(0, tb_rate_monitor);
    end

    // Sends one "packet" -- pulses pkt_valid for one cycle with
    // whatever header fields are currently set
    task send_packet;
        begin
            @(posedge clk);
            pkt_valid <= 1;
            @(posedge clk);
            pkt_valid <= 0;
        end
    endtask

    integer k;

    initial begin
        rst_n = 0;
        repeat(4) @(posedge clk);
        rst_n = 1;
        repeat(2) @(posedge clk);

        // -------------------------------------------------------
        // TEST 1: new flow insertion
        // -------------------------------------------------------
        $display("--- TEST 1: new flow insertion ---");
        src_ip   = 32'hC0A80101;  // 192.168.1.1
        dst_ip   = 32'h08080808;  // 8.8.8.8
        src_port = 16'd5000;
        dst_port = 16'd443;
        protocol = 8'h06;
        is_syn = 0; is_syn_ack = 0; is_arp_reply = 0;
        send_packet;
        repeat(2) @(posedge clk);

        $display("  u_dut.ft_valid[free_slot guess 0]=%b pkt_count[0]=%0d",
                  u_dut.ft_valid[0], u_dut.ft_pkt_count[0]);

        // -------------------------------------------------------
        // TEST 2: same flow again -- should update slot 0, not
        // create a second entry. pkt_count should go to 2.
        // -------------------------------------------------------
        $display("--- TEST 2: repeat same flow (expect pkt_count=2, same slot) ---");
        send_packet;
        repeat(2) @(posedge clk);
        $display("  ft_valid[0]=%b pkt_count[0]=%0d ft_valid[1]=%b",
                  u_dut.ft_valid[0], u_dut.ft_pkt_count[0], u_dut.ft_valid[1]);

        // -------------------------------------------------------
        // TEST 3: ARP spoofing -- send ARP_THRESH+1 = 21 ARP replies
        // -------------------------------------------------------
        $display("--- TEST 3: ARP spoof flood (21x ARP replies) ---");
        is_arp_reply = 1;
        for (k = 0; k < 21; k = k + 1) begin
            send_packet;
        end
        repeat(2) @(posedge clk);
        $display("  rate_alert=%b alert_type=%0d (expect 1, type=0 ARP spoof)",
                  rate_alert, alert_type);
        is_arp_reply = 0;
        repeat(4) @(posedge clk);

        // -------------------------------------------------------
        // TEST 4: SYN flood -- same NEW flow, 30+ SYNs, <5 SYN-ACKs
        // -------------------------------------------------------
        $display("--- TEST 4: SYN flood (31x SYN, 0x SYN-ACK, new flow) ---");
        src_ip   = 32'h0A000001;  // 10.0.0.1
        dst_ip   = 32'h0A000002;  // 10.0.0.2
        src_port = 16'd6000;
        dst_port = 16'd80;
        is_syn = 1; is_syn_ack = 0;
        for (k = 0; k < 31; k = k + 1) begin
            send_packet;
        end
        repeat(2) @(posedge clk);
        $display("  rate_alert=%b alert_type=%0d (expect 1, type=1 SYN flood)",
                  rate_alert, alert_type);
        is_syn = 0;
        repeat(4) @(posedge clk);

        // -------------------------------------------------------
        // TEST 5: C2 beaconing -- same flow, 50+ plain packets
        // -------------------------------------------------------
        $display("--- TEST 5: C2 beaconing (51x plain packets, same flow) ---");
        src_ip   = 32'hAC100001;  // 172.16.0.1
        dst_ip   = 32'hAC100002;  // 172.16.0.2
        src_port = 16'd7000;
        dst_port = 16'd4444;
        is_syn = 0; is_syn_ack = 0;
        for (k = 0; k < 51; k = k + 1) begin
            send_packet;
        end
        repeat(2) @(posedge clk);
        $display("  rate_alert=%b alert_type=%0d (expect 1, type=2 beaconing)",
                  rate_alert, alert_type);

        $display("Simulation complete.");
        $finish;
    end

endmodule

sim/tb_rate_monitor.vcd
$date
	Sun Jun 21 19:55:05 2026
$end
$version
	Icarus Verilog
$end
$timescale
	1ps
$end
$scope module tb_rate_monitor $end
$var wire 1 ! rate_alert $end
$var wire 2 " alert_type [1:0] $end
$var reg 1 # clk $end
$var reg 32 $ dst_ip [31:0] $end
$var reg 16 % dst_port [15:0] $end
$var reg 1 & is_arp_reply $end
$var reg 1 ' is_syn $end
$var reg 1 ( is_syn_ack $end
$var reg 1 ) pkt_valid $end
$var reg 8 * protocol [7:0] $end
$var reg 1 + rst_n $end
$var reg 32 , src_ip [31:0] $end
$var reg 16 - src_port [15:0] $end
$var integer 32 . k [31:0] $end
$scope module u_dut $end
$var wire 1 # clk $end
$var wire 32 / dst_ip [31:0] $end
$var wire 16 0 dst_port [15:0] $end
$var wire 1 & is_arp_reply $end
$var wire 1 ' is_syn $end
$var wire 1 ( is_syn_ack $end
$var wire 1 ) pkt_valid $end
$var wire 8 1 protocol [7:0] $end
$var wire 1 + rst_n $end
$var wire 32 2 src_ip [31:0] $end
$var wire 16 3 src_port [15:0] $end
$var parameter 8 4 ARP_THRESH $end
$var parameter 16 5 BEACON_THRESH $end
$var parameter 16 6 FLOW_AGE_MAX $end
$var parameter 32 7 FLOW_SLOTS $end
$var parameter 32 8 SLOT_BITS $end
$var parameter 8 9 SYN_THRESH $end
$var reg 2 : alert_type [1:0] $end
$var reg 8 ; arp_reply_count [7:0] $end
$var reg 20 < arp_window_timer [19:0] $end
$var reg 1 = free_found $end
$var reg 6 > free_slot [5:0] $end
$var reg 6 ? hash_idx [5:0] $end
$var reg 6 @ matched_slot [5:0] $end
$var reg 1 ! rate_alert $end
$var reg 1 A slot_hit $end
$var integer 32 B j [31:0] $end
$var integer 32 C s [31:0] $end
$scope function flow_hash $end
$var reg 32 D dip [31:0] $end
$var reg 16 E dp [15:0] $end
$var reg 32 F h [31:0] $end
$var reg 32 G sip [31:0] $end
$var reg 16 H sp [15:0] $end
$upscope $end
$upscope $end
$scope task send_packet $end
$upscope $end
$upscope $end
$enddefinitions $end
$comment Show the parameter values. $end
$dumpall
b11110 9
b110 8
b1000000 7
b1111111111111111 6
b110010 5
b10100 4
$end
#0
$dumpvars
b0 H
b0 G
b0 F
b0 E
b0 D
b1000000 C
b1000000 B
0A
b0 @
b0 ?
b0 >
1=
b0 <
b0 ;
b0 :
b0 3
b0 2
b0 1
b0 0
b0 /
bx .
b0 -
b0 ,
0+
b0 *
0)
0(
0'
0&
b0 %
b0 $
0#
b0 "
0!
$end
#4000
b1000000 B
1#
#8000
0#
#12000
b1000000 B
1#
#16000
0#
#20000
b1000000 B
1#
#24000
0#
#28000
b1 <
b1000000 B
1+
1#
#32000
0#
#36000
b10 <
b1000000 B
1#
#40000
0#
#44000
b11 <
b1000000 C
1=
b11001 ?
b11011011001010000000100010110010 F
b11000000101010000000000100000001 G
b1000000010000000100000001000 D
b1001110001000 H
b110111011 E
b1000000 B
b110 *
b110 1
b110111011 %
b110111011 0
b1001110001000 -
b1001110001000 3
b1000000010000000100000001000 $
b1000000010000000100000001000 /
b11000000101010000000000100000001 ,
b11000000101010000000000100000001 2
1#
#48000
0#
#52000
b100 <
1)
b1000000 B
1#
#56000
0#
#60000
b1 >
1A
b1000000 C
1=
b101 <
0)
b1000000 B
1#
#64000
0#
#68000
b110 <
b1000000 B
1#
#72000
0#
#76000
b111 <
b1000000 B
1#
#80000
0#
#84000
b1000 <
1)
b1000000 B
1#
#88000
0#
#92000
b1001 <
0)
b1000000 B
1#
#96000
0#
#100000
b1010 <
b1000000 B
1#
#104000
0#
#108000
b1011 <
b1000000 B
b0 .
1&
1#
#112000
0#
#116000
b1100 <
1)
b1000000 B
1#
#120000
0#
#124000
b1 ;
b1101 <
0)
b1000000 B
b1 .
1#
#128000
0#
#132000
b1110 <
1)
b1000000 B
1#
#136000
0#
#140000
b10 ;
b1111 <
0)
b1000000 B
b10 .
1#
#144000
0#
#148000
b10000 <
1)
b1000000 B
1#
#152000
0#
#156000
b11 ;
b10001 <
0)
b1000000 B
b11 .
1#
#160000
0#
#164000
b10010 <
1)
b1000000 B
1#
#168000
0#
#172000
b100 ;
b10011 <
0)
b1000000 B
b100 .
1#
#176000
0#
#180000
b10100 <
1)
b1000000 B
1#
#184000
0#
#188000
b101 ;
b10101 <
0)
b1000000 B
b101 .
1#
#192000
0#
#196000
b10110 <
1)
b1000000 B
1#
#200000
0#
#204000
b110 ;
b10111 <
0)
b1000000 B
b110 .
1#
#208000
0#
#212000
b11000 <
1)
b1000000 B
1#
#216000
0#
#220000
b111 ;
b11001 <
0)
b1000000 B
b111 .
1#
#224000
0#
#228000
b11010 <
1)
b1000000 B
1#
#232000
0#
#236000
b1000 ;
b11011 <
0)
b1000000 B
b1000 .
1#
#240000
0#
#244000
b11100 <
1)
b1000000 B
1#
#248000
0#
#252000
b1001 ;
b11101 <
0)
b1000000 B
b1001 .
1#
#256000
0#
#260000
b11110 <
1)
b1000000 B
1#
#264000
0#
#268000
b1010 ;
b11111 <
0)
b1000000 B
b1010 .
1#
#272000
0#
#276000
b100000 <
1)
b1000000 B
1#
#280000
0#
#284000
b1011 ;
b100001 <
0)
b1000000 B
b1011 .
1#
#288000
0#
#292000
b100010 <
1)
b1000000 B
1#
#296000
0#
#300000
b1100 ;
b100011 <
0)
b1000000 B
b1100 .
1#
#304000
0#
#308000
b100100 <
1)
b1000000 B
1#
#312000
0#
#316000
b1101 ;
b100101 <
0)
b1000000 B
b1101 .
1#
#320000
0#
#324000
b100110 <
1)
b1000000 B
1#
#328000
0#
#332000
b1110 ;
b100111 <
0)
b1000000 B
b1110 .
1#
#336000
0#
#340000
b101000 <
1)
b1000000 B
1#
#344000
0#
#348000
b1111 ;
b101001 <
0)
b1000000 B
b1111 .
1#
#352000
0#
#356000
b101010 <
1)
b1000000 B
1#
#360000
0#
#364000
b10000 ;
b101011 <
0)
b1000000 B
b10000 .
1#
#368000
0#
#372000
b101100 <
1)
b1000000 B
1#
#376000
0#
#380000
b10001 ;
b101101 <
0)
b1000000 B
b10001 .
1#
#384000
0#
#388000
b101110 <
1)
b1000000 B
1#
#392000
0#
#396000
b10010 ;
b101111 <
0)
b1000000 B
b10010 .
1#
#400000
0#
#404000
b110000 <
1)
b1000000 B
1#
#408000
0#
#412000
b10011 ;
b110001 <
0)
b1000000 B
b10011 .
1#
#416000
0#
#420000
b110010 <
1)
b1000000 B
1#
#424000
0#
#428000
b10100 ;
b110011 <
0)
b1000000 B
b10100 .
1#
#432000
0#
#436000
b110100 <
1)
b1000000 B
1#
#440000
0#
#444000
b10101 ;
b110101 <
1!
0)
b1000000 B
b10101 .
1#
#448000
0#
#452000
b110110 <
b1000000 B
1#
#456000
0#
#460000
b110111 <
b1000000 B
0&
1#
#464000
0#
#468000
b111000 <
b1000000 B
1#
#472000
0#
#476000
b111001 <
b1000000 B
1#
#480000
0#
#484000
b111010 <
b1000000 B
1#
#488000
0#
#492000
b111011 <
b1000000 C
1=
b1 >
0A
b1101 ?
b10111011100000000000001010011 F
b1010000000000000000000000001 G
b1010000000000000000000000010 D
b1011101110000 H
b1010000 E
b1000000 B
b0 .
1'
b1010000 %
b1010000 0
b1011101110000 -
b1011101110000 3
b1010000000000000000000000010 $
b1010000000000000000000000010 /
b1010000000000000000000000001 ,
b1010000000000000000000000001 2
1#
#496000
0#
#500000
b111100 <
1)
b1000000 B
1#
#504000
0#
#508000
1A
b1 @
b1000000 C
1=
b10 >
b111101 <
0)
b1000000 B
b1 .
1#
#512000
0#
#516000
b111110 <
1)
b1000000 B
1#
#520000
0#
#524000
b111111 <
0)
b1000000 B
b10 .
1#
#528000
0#
#532000
b1000000 <
1)
b1000000 B
1#
#536000
0#
#540000
b1000001 <
0)
b1000000 B
b11 .
1#
#544000
0#
#548000
b1000010 <
1)
b1000000 B
1#
#552000
0#
#556000
b1000011 <
0)
b1000000 B
b100 .
1#
#560000
0#
#564000
b1000100 <
1)
b1000000 B
1#
#568000
0#
#572000
b1000101 <
0)
b1000000 B
b101 .
1#
#576000
0#
#580000
b1000110 <
1)
b1000000 B
1#
#584000
0#
#588000
b1000111 <
0)
b1000000 B
b110 .
1#
#592000
0#
#596000
b1001000 <
1)
b1000000 B
1#
#600000
0#
#604000
b1001001 <
0)
b1000000 B
b111 .
1#
#608000
0#
#612000
b1001010 <
1)
b1000000 B
1#
#616000
0#
#620000
b1001011 <
0)
b1000000 B
b1000 .
1#
#624000
0#
#628000
b1001100 <
1)
b1000000 B
1#
#632000
0#
#636000
b1001101 <
0)
b1000000 B
b1001 .
1#
#640000
0#
#644000
b1001110 <
1)
b1000000 B
1#
#648000
0#
#652000
b1001111 <
0)
b1000000 B
b1010 .
1#
#656000
0#
#660000
b1010000 <
1)
b1000000 B
1#
#664000
0#
#668000
b1010001 <
0)
b1000000 B
b1011 .
1#
#672000
0#
#676000
b1010010 <
1)
b1000000 B
1#
#680000
0#
#684000
b1010011 <
0)
b1000000 B
b1100 .
1#
#688000
0#
#692000
b1010100 <
1)
b1000000 B
1#
#696000
0#
#700000
b1010101 <
0)
b1000000 B
b1101 .
1#
#704000
0#
#708000
b1010110 <
1)
b1000000 B
1#
#712000
0#
#716000
b1010111 <
0)
b1000000 B
b1110 .
1#
#720000
0#
#724000
b1011000 <
1)
b1000000 B
1#
#728000
0#
#732000
b1011001 <
0)
b1000000 B
b1111 .
1#
#736000
0#
#740000
b1011010 <
1)
b1000000 B
1#
#744000
0#
#748000
b1011011 <
0)
b1000000 B
b10000 .
1#
#752000
0#
#756000
b1011100 <
1)
b1000000 B
1#
#760000
0#
#764000
b1011101 <
0)
b1000000 B
b10001 .
1#
#768000
0#
#772000
b1011110 <
1)
b1000000 B
1#
#776000
0#
#780000
b1011111 <
0)
b1000000 B
b10010 .
1#
#784000
0#
#788000
b1100000 <
1)
b1000000 B
1#
#792000
0#
#796000
b1100001 <
0)
b1000000 B
b10011 .
1#
#800000
0#
#804000
b1100010 <
1)
b1000000 B
1#
#808000
0#
#812000
b1100011 <
0)
b1000000 B
b10100 .
1#
#816000
0#
#820000
b1100100 <
1)
b1000000 B
1#
#824000
0#
#828000
b1100101 <
0)
b1000000 B
b10101 .
1#
#832000
0#
#836000
b1100110 <
1)
b1000000 B
1#
#840000
0#
#844000
b1100111 <
0)
b1000000 B
b10110 .
1#
#848000
0#
#852000
b1101000 <
1)
b1000000 B
1#
#856000
0#
#860000
b1101001 <
0)
b1000000 B
b10111 .
1#
#864000
0#
#868000
b1101010 <
1)
b1000000 B
1#
#872000
0#
#876000
b1101011 <
0)
b1000000 B
b11000 .
1#
#880000
0#
#884000
b1101100 <
1)
b1000000 B
1#
#888000
0#
#892000
b1101101 <
0)
b1000000 B
b11001 .
1#
#896000
0#
#900000
b1101110 <
1)
b1000000 B
1#
#904000
0#
#908000
b1101111 <
0)
b1000000 B
b11010 .
1#
#912000
0#
#916000
b1110000 <
1)
b1000000 B
1#
#920000
0#
#924000
b1110001 <
0)
b1000000 B
b11011 .
1#
#928000
0#
#932000
b1110010 <
1)
b1000000 B
1#
#936000
0#
#940000
b1110011 <
0)
b1000000 B
b11100 .
1#
#944000
0#
#948000
b1110100 <
1)
b1000000 B
1#
#952000
0#
#956000
b1110101 <
0)
b1000000 B
b11101 .
1#
#960000
0#
#964000
b1110110 <
1)
b1000000 B
1#
#968000
0#
#972000
b1110111 <
b1 "
b1 :
0)
b1000000 B
b11110 .
1#
#976000
0#
#980000
b1111000 <
1)
b1000000 B
1#
#984000
0#
#988000
b1111001 <
0)
b1000000 B
b11111 .
1#
#992000
0#
#996000
b1111010 <
b1000000 B
1#
#1000000
0#
#1004000
b1111011 <
b1000000 B
0'
1#
#1008000
0#
#1012000
b1111100 <
b1000000 B
1#
#1016000
0#
#1020000
b1111101 <
b1000000 B
1#
#1024000
0#
#1028000
b1111110 <
b1000000 B
1#
#1032000
0#
#1036000
b1111111 <
b1000000 C
1=
b10 >
0A
b0 @
b1110 ?
b11011010110000001000101011111 F
b10101100000100000000000000000001 G
b10101100000100000000000000000010 D
b1101101011000 H
b1000101011100 E
b1000000 B
b0 .
b1000101011100 %
b1000101011100 0
b1101101011000 -
b1101101011000 3
b10101100000100000000000000000010 $
b10101100000100000000000000000010 /
b10101100000100000000000000000001 ,
b10101100000100000000000000000001 2
1#
#1040000
0#
#1044000
b10000000 <
1)
b1000000 B
1#
#1048000
0#
#1052000
1A
b10 @
b1000000 C
1=
b11 >
b10000001 <
0)
b1000000 B
b1 .
1#
#1056000
0#
#1060000
b10000010 <
1)
b1000000 B
1#
#1064000
0#
#1068000
b10000011 <
0)
b1000000 B
b10 .
1#
#1072000
0#
#1076000
b10000100 <
1)
b1000000 B
1#
#1080000
0#
#1084000
b10000101 <
0)
b1000000 B
b11 .
1#
#1088000
0#
#1092000
b10000110 <
1)
b1000000 B
1#
#1096000
0#
#1100000
b10000111 <
0)
b1000000 B
b100 .
1#
#1104000
0#
#1108000
b10001000 <
1)
b1000000 B
1#
#1112000
0#
#1116000
b10001001 <
0)
b1000000 B
b101 .
1#
#1120000
0#
#1124000
b10001010 <
1)
b1000000 B
1#
#1128000
0#
#1132000
b10001011 <
0)
b1000000 B
b110 .
1#
#1136000
0#
#1140000
b10001100 <
1)
b1000000 B
1#
#1144000
0#
#1148000
b10001101 <
0)
b1000000 B
b111 .
1#
#1152000
0#
#1156000
b10001110 <
1)
b1000000 B
1#
#1160000
0#
#1164000
b10001111 <
0)
b1000000 B
b1000 .
1#
#1168000
0#
#1172000
b10010000 <
1)
b1000000 B
1#
#1176000
0#
#1180000
b10010001 <
0)
b1000000 B
b1001 .
1#
#1184000
0#
#1188000
b10010010 <
1)
b1000000 B
1#
#1192000
0#
#1196000
b10010011 <
0)
b1000000 B
b1010 .
1#
#1200000
0#
#1204000
b10010100 <
1)
b1000000 B
1#
#1208000
0#
#1212000
b10010101 <
0)
b1000000 B
b1011 .
1#
#1216000
0#
#1220000
b10010110 <
1)
b1000000 B
1#
#1224000
0#
#1228000
b10010111 <
0)
b1000000 B
b1100 .
1#
#1232000
0#
#1236000
b10011000 <
1)
b1000000 B
1#
#1240000
0#
#1244000
b10011001 <
0)
b1000000 B
b1101 .
1#
#1248000
0#
#1252000
b10011010 <
1)
b1000000 B
1#
#1256000
0#
#1260000
b10011011 <
0)
b1000000 B
b1110 .
1#
#1264000
0#
#1268000
b10011100 <
1)
b1000000 B
1#
#1272000
0#
#1276000
b10011101 <
0)
b1000000 B
b1111 .
1#
#1280000
0#
#1284000
b10011110 <
1)
b1000000 B
1#
#1288000
0#
#1292000
b10011111 <
0)
b1000000 B
b10000 .
1#
#1296000
0#
#1300000
b10100000 <
1)
b1000000 B
1#
#1304000
0#
#1308000
b10100001 <
0)
b1000000 B
b10001 .
1#
#1312000
0#
#1316000
b10100010 <
1)
b1000000 B
1#
#1320000
0#
#1324000
b10100011 <
0)
b1000000 B
b10010 .
1#
#1328000
0#
#1332000
b10100100 <
1)
b1000000 B
1#
#1336000
0#
#1340000
b10100101 <
0)
b1000000 B
b10011 .
1#
#1344000
0#
#1348000
b10100110 <
1)
b1000000 B
1#
#1352000
0#
#1356000
b10100111 <
0)
b1000000 B
b10100 .
1#
#1360000
0#
#1364000
b10101000 <
1)
b1000000 B
1#
#1368000
0#
#1372000
b10101001 <
0)
b1000000 B
b10101 .
1#
#1376000
0#
#1380000
b10101010 <
1)
b1000000 B
1#
#1384000
0#
#1388000
b10101011 <
0)
b1000000 B
b10110 .
1#
#1392000
0#
#1396000
b10101100 <
1)
b1000000 B
1#
#1400000
0#
#1404000
b10101101 <
0)
b1000000 B
b10111 .
1#
#1408000
0#
#1412000
b10101110 <
1)
b1000000 B
1#
#1416000
0#
#1420000
b10101111 <
0)
b1000000 B
b11000 .
1#
#1424000
0#
#1428000
b10110000 <
1)
b1000000 B
1#
#1432000
0#
#1436000
b10110001 <
0)
b1000000 B
b11001 .
1#
#1440000
0#
#1444000
b10110010 <
1)
b1000000 B
1#
#1448000
0#
#1452000
b10110011 <
0)
b1000000 B
b11010 .
1#
#1456000
0#
#1460000
b10110100 <
1)
b1000000 B
1#
#1464000
0#
#1468000
b10110101 <
0)
b1000000 B
b11011 .
1#
#1472000
0#
#1476000
b10110110 <
1)
b1000000 B
1#
#1480000
0#
#1484000
b10110111 <
0)
b1000000 B
b11100 .
1#
#1488000
0#
#1492000
b10111000 <
1)
b1000000 B
1#
#1496000
0#
#1500000
b10111001 <
0)
b1000000 B
b11101 .
1#
#1504000
0#
#1508000
b10111010 <
1)
b1000000 B
1#
#1512000
0#
#1516000
b10111011 <
0)
b1000000 B
b11110 .
1#
#1520000
0#
#1524000
b10111100 <
1)
b1000000 B
1#
#1528000
0#
#1532000
b10111101 <
0)
b1000000 B
b11111 .
1#
#1536000
0#
#1540000
b10111110 <
1)
b1000000 B
1#
#1544000
0#
#1548000
b10111111 <
0)
b1000000 B
b100000 .
1#
#1552000
0#
#1556000
b11000000 <
1)
b1000000 B
1#
#1560000
0#
#1564000
b11000001 <
0)
b1000000 B
b100001 .
1#
#1568000
0#
#1572000
b11000010 <
1)
b1000000 B
1#
#1576000
0#
#1580000
b11000011 <
0)
b1000000 B
b100010 .
1#
#1584000
0#
#1588000
b11000100 <
1)
b1000000 B
1#
#1592000
0#
#1596000
b11000101 <
0)
b1000000 B
b100011 .
1#
#1600000
0#
#1604000
b11000110 <
1)
b1000000 B
1#
#1608000
0#
#1612000
b11000111 <
0)
b1000000 B
b100100 .
1#
#1616000
0#
#1620000
b11001000 <
1)
b1000000 B
1#
#1624000
0#
#1628000
b11001001 <
0)
b1000000 B
b100101 .
1#
#1632000
0#
#1636000
b11001010 <
1)
b1000000 B
1#
#1640000
0#
#1644000
b11001011 <
0)
b1000000 B
b100110 .
1#
#1648000
0#
#1652000
b11001100 <
1)
b1000000 B
1#
#1656000
0#
#1660000
b11001101 <
0)
b1000000 B
b100111 .
1#
#1664000
0#
#1668000
b11001110 <
1)
b1000000 B
1#
#1672000
0#
#1676000
b11001111 <
0)
b1000000 B
b101000 .
1#
#1680000
0#
#1684000
b11010000 <
1)
b1000000 B
1#
#1688000
0#
#1692000
b11010001 <
0)
b1000000 B
b101001 .
1#
#1696000
0#
#1700000
b11010010 <
1)
b1000000 B
1#
#1704000
0#
#1708000
b11010011 <
0)
b1000000 B
b101010 .
1#
#1712000
0#
#1716000
b11010100 <
1)
b1000000 B
1#
#1720000
0#
